Workbook

Sheet Census Data
A1: Last updated | B1: State | C1: Type of Data | D1: Description | E1: Exists | F1: Digitized | G1: Public | H1: Free | I1: Online | J1: Machine readable | K1: Available in bulk | L1: No restrictions | M1: Up-to-date | N1: In the state repository | O1: Verifiable | P1: Complete | Q1: Link | R1: Comments | S1: Score | T1: Grade
A2: 42349 | B2: Alabama | C2: Address Points | D2: =IF(NOT(ISBLANK(C2)), VLOOKUP(C2,'Dataset Descriptions'!$A$2:$B$10, 2, FALSE), "") -> The geographic coordinates for physical addresses. | E2: unsure | F2: unsure | G2: unsure | H2: unsure | I2: no | J2: unsure | K2: no | L2: unsure | M2: unsure | N2: no | O2: no | P2: unsure | S2: =IF(NOT(ISBLANK(E2)), ROUND(((IF(E2="yes",1,0)*'Grading Scale'!E$2)+(IF(F2="yes",1,0)*'Grading Scale'!E$3)+(IF(G2="yes",1,0)*'Grading Scale'!E$4)+(IF(H2="yes",1,0)*'Grading Scale'!E$5)+(IF(I2="yes",1,0)*'Grading Scale'!E$6)+(IF(J2="yes",1,0)*'Grading Scale'!E$7)+(IF(K2="yes",1,0)*'Grading Scale'!E$8)+(IF(L2="yes",1,0)*'Grading Scale'!E$9)+(IF(M2="yes",1,0)*'Grading Scale'!E$10)+(IF(N2="yes",1,0)*'Grading Scale'!E$11)+(IF(O2="yes",1,0)*'Grading Scale'!E$12)+(IF(P2="yes",1,0)*'Grading Scale'!E$13))/'Grading Scale'!E$14*100,0), "") -> 0 | T2: =IF(ISNUMBER(S2),VLOOKUP(S2,'Grading Scale'!$A$2:$B$14, 2), "") -> F
A3: 42459 | B3: Alabama | C3: Checkbook | D3: =IF(NOT(ISBLANK(C3)), VLOOKUP(C3,'Dataset Descriptions'!$A$2:$B$10, 2, FALSE), "") -> Transaction-level, per-agency spending records. | E3: yes | F3: yes | G3: yes | H3: yes | I3: yes | J3: no | K3: no | L3: yes | M3: no | N3: no | O3: no | P3: no | Q3: http://open.alabama.gov/spending_checkbook.aspx | R3: At the time that it was surveyed, the data had not been updated for over two months. Does not include a description of the purpose of the expenditure. The results of queries can be exported as Excel files, but so few record-level results can be exported at one time that this hardly quaifies as offering machine-readable data. | S3: =IF(NOT(ISBLANK(E3)), ROUND(((IF(E3="yes",1,0)*'Grading Scale'!E$2)+(IF(F3="yes",1,0)*'Grading Scale'!E$3)+(IF(G3="yes",1,0)*'Grading Scale'!E$4)+(IF(H3="yes",1,0)*'Grading Scale'!E$5)+(IF(I3="yes",1,0)*'Grading Scale'!E$6)+(IF(J3="yes",1,0)*'Grading Scale'!E$7)+(IF(K3="yes",1,0)*'Grading Scale'!E$8)+(IF(L3="yes",1,0)*'Grading Scale'!E$9)+(IF(M3="yes",1,0)*'Grading Scale'!E$10)+(IF(N3="yes",1,0)*'Grading Scale'!E$11)+(IF(O3="yes",1,0)*'Grading Scale'!E$12)+(IF(P3="yes",1,0)*'Grading Scale'!E$13))/'Grading Scale'!E$14*100,0), "") -> 35 | T3: =IF(ISNUMBER(S3),VLOOKUP(S3,'Grading Scale'!$A$2:$B$14, 2), "") -> F
A4: 42349 | B4: Alabama | C4: Companies | D4: =IF(NOT(ISBLANK(C4)), VLOOKUP(C4,'Dataset Descriptions'!$A$2:$B$10, 2, FALSE), "") -> The register of all corporations that exist in the state. | E4: yes | F4: yes | G4: yes | H4: yes | I4: yes | J4: no | K4: no | L4: no | M4: no | N4: no | O4: no | P4: yes | Q4: http://arc-sos.state.al.us/CGI/CORPNAME.MBR/INPUT | R4: At the time that it was surveyed, the data was 6 weeks out of date. | S4: =IF(NOT(ISBLANK(E4)), ROUND(((IF(E4="yes",1,0)*'Grading Scale'!E$2)+(IF(F4="yes",1,0)*'Grading Scale'!E$3)+(IF(G4="yes",1,0)*'Grading Scale'!E$4)+(IF(H4="yes",1,0)*'Grading Scale'!E$5)+(IF(I4="yes",1,0)*'Grading Scale'!E$6)+(IF(J4="yes",1,0)*'Grading Scale'!E$7)+(IF(K4="yes",1,0)*'Grading Scale'!E$8)+(IF(L4="yes",1,0)*'Grading Scale'!E$9)+(IF(M4="yes",1,0)*'Grading Scale'!E$10)+(IF(N4="yes",1,0)*'Grading Scale'!E$11)+(IF(O4="yes",1,0)*'Grading Scale'!E$12)+(IF(P4="yes",1,0)*'Grading Scale'!E$13))/'Grading Scale'!E$14*100,0), "") -> 35 | T4: =IF(ISNUMBER(S4),VLOOKUP(S4,'Grading Scale'!$A$2:$B$14, 2), "") -> F
A5: 42349 | B5: Alabama | C5: Incarceration | D5: =IF(NOT(ISBLANK(C5)), VLOOKUP(C5,'Dataset Descriptions'!$A$2:$B$10, 2, FALSE), "") -> Per-facility inmate population records. | E5: yes | F5: yes | G5: yes | H5: yes | I5: yes | J5: no | K5: yes | L5: no | M5: no | N5: no | O5: no | P5: yes | Q5: http://www.doc.state.al.us/StatReports.aspx | R5: At the time that it was surveyed, data was over two months old. | S5: =IF(NOT(ISBLANK(E5)), ROUND(((IF(E5="yes",1,0)*'Grading Scale'!E$2)+(IF(F5="yes",1,0)*'Grading Scale'!E$3)+(IF(G5="yes",1,0)*'Grading Scale'!E$4)+(IF(H5="yes",1,0)*'Grading Scale'!E$5)+(IF(I5="yes",1,0)*'Grading Scale'!E$6)+(IF(J5="yes",1,0)*'Grading Scale'!E$7)+(IF(K5="yes",1,0)*'Grading Scale'!E$8)+(IF(L5="yes",1,0)*'Grading Scale'!E$9)+(IF(M5="yes",1,0)*'Grading Scale'!E$10)+(IF(N5="yes",1,0)*'Grading Scale'!E$11)+(IF(O5="yes",1,0)*'Grading Scale'!E$12)+(IF(P5="yes",1,0)*'Grading Scale'!E$13))/'Grading Scale'!E$14*100,0), "") -> 40 | T5: =IF(ISNUMBER(S5),VLOOKUP(S5,'Grading Scale'!$A$2:$B$14, 2), "") -> F
A6: 42349 | B6: Alabama | C6: Legislation | D6: =IF(NOT(ISBLANK(C6)), VLOOKUP(C6,'Dataset Descriptions'!$A$2:$B$10, 2, FALSE), "") -> Bills before the legislature, and the legislators that comprise it. | E6: yes | F6: yes | G6: yes | H6: yes | I6: yes | J6: no | K6: no | L6: yes | M6: unsure | N6: no | O6: no | P6: unsure | Q6: http://www.legislature.state.al.us/ | R6: This is surely the worst legislative website in the nation. It is such a mess that it is difficult to assess meaningfully. | S6: =IF(NOT(ISBLANK(E6)), ROUND(((IF(E6="yes",1,0)*'Grading Scale'!E$2)+(IF(F6="yes",1,0)*'Grading Scale'!E$3)+(IF(G6="yes",1,0)*'Grading Scale'!E$4)+(IF(H6="yes",1,0)*'Grading Scale'!E$5)+(IF(I6="yes",1,0)*'Grading Scale'!E$6)+(IF(J6="yes",1,0)*'Grading Scale'!E$7)+(IF(K6="yes",1,0)*'Grading Scale'!E$8)+(IF(L6="yes",1,0)*'Grading Scale'!E$9)+(IF(M6="yes",1,0)*'Grading Scale'!E$10)+(IF(N6="yes",1,0)*'Grading Scale'!E$11)+(IF(O6="yes",1,0)*'Grading Scale'!E$12)+(IF(P6="yes",1,0)*'Grading Scale'!E$13))/'Grading Scale'!E$14*100,0), "") -> 35 | T6: =IF(ISNUMBER(S6),VLOOKUP(S6,'Grading Scale'!$A$2:$B$14, 2), "") -> F
A7: 42349 | B7: Alabama | C7: Population Projections | D7: =IF(NOT(ISBLANK(C7)), VLOOKUP(C7,'Dataset Descriptions'!$A$2:$B$10, 2, FALSE), "") -> Forecasts of municipal-level changes in population over coming years. | E7: yes | F7: yes | G7: yes | H7: yes | I7: yes | J7: yes | K7: no | L7: yes | M7: yes | N7: no | O7: no | P7: no | Q7: http://cber.cba.ua.edu/edata/est_prj.html | R7: Lacks GNIS IDs for localities. | S7: =IF(NOT(ISBLANK(E7)), ROUND(((IF(E7="yes",1,0)*'Grading Scale'!E$2)+(IF(F7="yes",1,0)*'Grading Scale'!E$3)+(IF(G7="yes",1,0)*'Grading Scale'!E$4)+(IF(H7="yes",1,0)*'Grading Scale'!E$5)+(IF(I7="yes",1,0)*'Grading Scale'!E$6)+(IF(J7="yes",1,0)*'Grading Scale'!E$7)+(IF(K7="yes",1,0)*'Grading Scale'!E$8)+(IF(L7="yes",1,0)*'Grading Scale'!E$9)+(IF(M7="yes",1,0)*'Grading Scale'!E$10)+(IF(N7="yes",1,0)*'Grading Scale'!E$11)+(IF(O7="yes",1,0)*'Grading Scale'!E$12)+(IF(P7="yes",1,0)*'Grading Scale'!E$13))/'Grading Scale'!E$14*100,0), "") -> 80 | T7: =IF(ISNUMBER(S7),VLOOKUP(S7,'Grading Scale'!$A$2:$B$14, 2), "") -> B−
A8: 42349 | B8: Alabama | C8: Real Estate | D8: =IF(NOT(ISBLANK(C8)), VLOOKUP(C8,'Dataset Descriptions'!$A$2:$B$10, 2, FALSE), "") -> State-owned land and buildings. | E8: yes | F8: yes | G8: yes | H8: yes | I8: yes | J8: no | K8: no | L8: no | M8: unsure | N8: no | O8: no | P8: no | Q8: http://open.alabama.gov/state_properties.aspx | R8: The use of each facility is not specified. The data is split between three unrelated websites (one for leased buildings, one for owned buildings, and one for land). Dates are not included for most records, so it is difficult to determine if the data is up-to-date. | S8: =IF(NOT(ISBLANK(E8)), ROUND(((IF(E8="yes",1,0)*'Grading Scale'!E$2)+(IF(F8="yes",1,0)*'Grading Scale'!E$3)+(IF(G8="yes",1,0)*'Grading Scale'!E$4)+(IF(H8="yes",1,0)*'Grading Scale'!E$5)+(IF(I8="yes",1,0)*'Grading Scale'!E$6)+(IF(J8="yes",1,0)*'Grading Scale'!E$7)+(IF(K8="yes",1,0)*'Grading Scale'!E$8)+(IF(L8="yes",1,0)*'Grading Scale'!E$9)+(IF(M8="yes",1,0)*'Grading Scale'!E$10)+(IF(N8="yes",1,0)*'Grading Scale'!E$11)+(IF(O8="yes",1,0)*'Grading Scale'!E$12)+(IF(P8="yes",1,0)*'Grading Scale'!E$13))/'Grading Scale'!E$14*100,0), "") -> 30 | T8: =IF(ISNUMBER(S8),VLOOKUP(S8,'Grading Scale'!$A$2:$B$14, 2), "") -> F
A9: 42349 | B9: Alabama | C9: Restaurant Inspections | D9: =IF(NOT(ISBLANK(C9)), VLOOKUP(C9,'Dataset Descriptions'!$A$2:$B$10, 2, FALSE), "") -> Health inspections of establishments that serve food to the public. | E9: yes | F9: yes | G9: yes | H9: yes | I9: yes | J9: no | K9: no | L9: yes | M9: yes | N9: no | O9: no | P9: no | Q9: http://foodscores.state.al.us/ | R9: Does not include unique identifiers or the outcome of inspections (passed, failed, etc.) | S9: =IF(NOT(ISBLANK(E9)), ROUND(((IF(E9="yes",1,0)*'Grading Scale'!E$2)+(IF(F9="yes",1,0)*'Grading Scale'!E$3)+(IF(G9="yes",1,0)*'Grading Scale'!E$4)+(IF(H9="yes",1,0)*'Grading Scale'!E$5)+(IF(I9="yes",1,0)*'Grading Scale'!E$6)+(IF(J9="yes",1,0)*'Grading Scale'!E$7)+(IF(K9="yes",1,0)*'Grading Scale'!E$8)+(IF(L9="yes",1,0)*'Grading Scale'!E$9)+(IF(M9="yes",1,0)*'Grading Scale'!E$10)+(IF(N9="yes",1,0)*'Grading Scale'!E$11)+(IF(O9="yes",1,0)*'Grading Scale'!E$12)+(IF(P9="yes",1,0)*'Grading Scale'!E$13))/'Grading Scale'!E$14*100,0), "") -> 40 | T9: =IF(ISNUMBER(S9),VLOOKUP(S9,'Grading Scale'!$A$2:$B$14, 2), "") -> F
A10: 42349 | B10: Alabama | C10: Vehicle Crashes | D10: =IF(NOT(ISBLANK(C10)), VLOOKUP(C10,'Dataset Descriptions'!$A$2:$B$10, 2, FALSE), "") -> Incident-level reportable motor vehicle crash records. | E10: yes | F10: yes | G10: yes | H10: yes | I10: yes | J10: no | K10: no | L10: yes | M10: no | N10: no | O10: no | P10: no | Q10: http://www.dot.state.al.us/mcrweb/frm/Crash_Facts.pdf | R10: This is a PDF from 2012, containing statistics, not raw data. This is the best data source that could be identified. | S10: =IF(NOT(ISBLANK(E10)), ROUND(((IF(E10="yes",1,0)*'Grading Scale'!E$2)+(IF(F10="yes",1,0)*'Grading Scale'!E$3)+(IF(G10="yes",1,0)*'Grading Scale'!E$4)+(IF(H10="yes",1,0)*'Grading Scale'!E$5)+(IF(I10="yes",1,0)*'Grading Scale'!E$6)+(IF(J10="yes",1,0)*'Grading Scale'!E$7)+(IF(K10="yes",1,0)*'Grading Scale'!E$8)+(IF(L10="yes",1,0)*'Grading Scale'!E$9)+(IF(M10="yes",1,0)*'Grading Scale'!E$10)+(IF(N10="yes",1,0)*'Grading Scale'!E$11)+(IF(O10="yes",1,0)*'Grading Scale'!E$12)+(IF(P10="yes",1,0)*'Grading Scale'!E$13))/'Grading Scale'!E$14*100,0), "") -> 35 | T10: =IF(ISNUMBER(S10),VLOOKUP(S10,'Grading Scale'!$A$2:$B$14, 2), "") -> F
A11: 42408 | B11: Alaska | C11: Address Points | D11: =IF(NOT(ISBLANK(C11)), VLOOKUP(C11,'Dataset Descriptions'!$A$2:$B$10, 2, FALSE), "") -> The geographic coordinates for physical addresses. | E11: unsure | F11: unsure | G11: unsure | H11: unsure | I11: no | J11: unsure | K11: unsure | L11: unsure | M11: unsure | N11: no | O11: unsure | P11: unsure | S11: =IF(NOT(ISBLANK(E11)), ROUND(((IF(E11="yes",1,0)*'Grading Scale'!E$2)+(IF(F11="yes",1,0)*'Grading Scale'!E$3)+(IF(G11="yes",1,0)*'Grading Scale'!E$4)+(IF(H11="yes",1,0)*'Grading Scale'!E$5)+(IF(I11="yes",1,0)*'Grading Scale'!E$6)+(IF(J11="yes",1,0)*'Grading Scale'!E$7)+(IF(K11="yes",1,0)*'Grading Scale'!E$8)+(IF(L11="yes",1,0)*'Grading Scale'!E$9)+(IF(M11="yes",1,0)*'Grading Scale'!E$10)+(IF(N11="yes",1,0)*'Grading Scale'!E$11)+(IF(O11="yes",1,0)*'Grading Scale'!E$12)+(IF(P11="yes",1,0)*'Grading Scale'!E$13))/'Grading Scale'!E$14*100,0), "") -> 0 | T11: =IF(ISNUMBER(S11),VLOOKUP(S11,'Grading Scale'!$A$2:$B$14, 2), "") -> F
A12: 42408 | B12: Alaska | C12: Checkbook | D12: =IF(NOT(ISBLANK(C12)), VLOOKUP(C12,'Dataset Descriptions'!$A$2:$B$10, 2, FALSE), "") -> Transaction-level, per-agency spending records. | E12: yes | F12: yes | G12: yes | H12: yes | I12: yes | J12: yes | K12: yes | L12: yes | M12: yes | N12: no | O12: no | P12: no | Q12: http://doa.alaska.gov/dof/reports/ckbkonline_reports.html | R12: Incomplete, because transaction records lack a description of their purpose and a check or voucher number. | S12: =IF(NOT(ISBLANK(E12)), ROUND(((IF(E12="yes",1,0)*'Grading Scale'!E$2)+(IF(F12="yes",1,0)*'Grading Scale'!E$3)+(IF(G12="yes",1,0)*'Grading Scale'!E$4)+(IF(H12="yes",1,0)*'Grading Scale'!E$5)+(IF(I12="yes",1,0)*'Grading Scale'!E$6)+(IF(J12="yes",1,0)*'Grading Scale'!E$7)+(IF(K12="yes",1,0)*'Grading Scale'!E$8)+(IF(L12="yes",1,0)*'Grading Scale'!E$9)+(IF(M12="yes",1,0)*'Grading Scale'!E$10)+(IF(N12="yes",1,0)*'Grading Scale'!E$11)+(IF(O12="yes",1,0)*'Grading Scale'!E$12)+(IF(P12="yes",1,0)*'Grading Scale'!E$13))/'Grading Scale'!E$14*100,0), "") -> 85 | T12: =IF(ISNUMBER(S12),VLOOKUP(S12,'Grading Scale'!$A$2:$B$14, 2), "") -> B
A13: 42408 | B13: Alaska | C13: Companies | D13: =IF(NOT(ISBLANK(C13)), VLOOKUP(C13,'Dataset Descriptions'!$A$2:$B$10, 2, FALSE), "") -> The register of all corporations that exist in the state. | E13: yes | F13: yes | G13: yes | H13: yes | I13: yes | J13: yes | K13: yes | L13: no | M13: yes | N13: no | O13: yes | P13: yes | Q13: https://www.commerce.alaska.gov/cbp/Main/CBPLSearch.aspx?mode=Corp | R13: Data is available in links in the sidebar. | S13: =IF(NOT(ISBLANK(E13)), ROUND(((IF(E13="yes",1,0)*'Grading Scale'!E$2)+(IF(F13="yes",1,0)*'Grading Scale'!E$3)+(IF(G13="yes",1,0)*'Grading Scale'!E$4)+(IF(H13="yes",1,0)*'Grading Scale'!E$5)+(IF(I13="yes",1,0)*'Grading Scale'!E$6)+(IF(J13="yes",1,0)*'Grading Scale'!E$7)+(IF(K13="yes",1,0)*'Grading Scale'!E$8)+(IF(L13="yes",1,0)*'Grading Scale'!E$9)+(IF(M13="yes",1,0)*'Grading Scale'!E$10)+(IF(N13="yes",1,0)*'Grading Scale'!E$11)+(IF(O13="yes",1,0)*'Grading Scale'!E$12)+(IF(P13="yes",1,0)*'Grading Scale'!E$13))/'Grading Scale'!E$14*100,0), "") -> 90 | T13: =IF(ISNUMBER(S13),VLOOKUP(S13,'Grading Scale'!$A$2:$B$14, 2), "") -> A−
A14: 42408 | B14: Alaska | C14: Incarceration | D14: =IF(NOT(ISBLANK(C14)), VLOOKUP(C14,'Dataset Descriptions'!$A$2:$B$10, 2, FALSE), "") -> Per-facility inmate population records. | E14: yes | F14: yes | G14: yes | H14: yes | I14: yes | J14: no | K14: yes | L14: yes | M14: yes | N14: no | O14: no | P14: no | Q14: http://www.correct.state.ak.us/administrative-services/research-records | R14: Provided as a PDF, as a small part of a much larger annual report. Incomplete as it lacks historical figures and facility capacity data. Updated annually. | S14: =IF(NOT(ISBLANK(E14)), ROUND(((IF(E14="yes",1,0)*'Grading Scale'!E$2)+(IF(F14="yes",1,0)*'Grading Scale'!E$3)+(IF(G14="yes",1,0)*'Grading Scale'!E$4)+(IF(H14="yes",1,0)*'Grading Scale'!E$5)+(IF(I14="yes",1,0)*'Grading Scale'!E$6)+(IF(J14="yes",1,0)*'Grading Scale'!E$7)+(IF(K14="yes",1,0)*'Grading Scale'!E$8)+(IF(L14="yes",1,0)*'Grading Scale'!E$9)+(IF(M14="yes",1,0)*'Grading Scale'!E$10)+(IF(N14="yes",1,0)*'Grading Scale'!E$11)+(IF(O14="yes",1,0)*'Grading Scale'!E$12)+(IF(P14="yes",1,0)*'Grading Scale'!E$13))/'Grading Scale'!E$14*100,0), "") -> 45 | T14: =IF(ISNUMBER(S14),VLOOKUP(S14,'Grading Scale'!$A$2:$B$14, 2), "") -> F
A15: 42408 | B15: Alaska | C15: Legislation | D15: =IF(NOT(ISBLANK(C15)), VLOOKUP(C15,'Dataset Descriptions'!$A$2:$B$10, 2, FALSE), "") -> Bills before the legislature, and the legislators that comprise it. | E15: yes | F15: yes | G15: yes | H15: yes | I15: yes | J15: no | K15: no | L15: no | M15: yes | N15: no | O15: no | P15: no | Q15: http://www.legis.state.ak.us/ | R15: Incomplete, because it does not specify the date that legislators took office. | S15: =IF(NOT(ISBLANK(E15)), ROUND(((IF(E15="yes",1,0)*'Grading Scale'!E$2)+(IF(F15="yes",1,0)*'Grading Scale'!E$3)+(IF(G15="yes",1,0)*'Grading Scale'!E$4)+(IF(H15="yes",1,0)*'Grading Scale'!E$5)+(IF(I15="yes",1,0)*'Grading Scale'!E$6)+(IF(J15="yes",1,0)*'Grading Scale'!E$7)+(IF(K15="yes",1,0)*'Grading Scale'!E$8)+(IF(L15="yes",1,0)*'Grading Scale'!E$9)+(IF(M15="yes",1,0)*'Grading Scale'!E$10)+(IF(N15="yes",1,0)*'Grading Scale'!E$11)+(IF(O15="yes",1,0)*'Grading Scale'!E$12)+(IF(P15="yes",1,0)*'Grading Scale'!E$13))/'Grading Scale'!E$14*100,0), "") -> 35 | T15: =IF(ISNUMBER(S15),VLOOKUP(S15,'Grading Scale'!$A$2:$B$14, 2), "") -> F
A16: 42408 | B16: Alaska | C16: Population Projections | D16: =IF(NOT(ISBLANK(C16)), VLOOKUP(C16,'Dataset Descriptions'!$A$2:$B$10, 2, FALSE), "") -> Forecasts of municipal-level changes in population over coming years. | E16: yes | F16: yes | G16: yes | H16: yes | I16: yes | J16: yes | K16: yes | L16: no | M16: yes | N16: no | O16: no | P16: no | Q16: http://labor.alaska.gov/research/pop/popproj.htm | R16: Forecasts are broken down by boroughs and census areas, but no FIPS codes or GNIS IDs are provided for them, making the data incomplete. | S16: =IF(NOT(ISBLANK(E16)), ROUND(((IF(E16="yes",1,0)*'Grading Scale'!E$2)+(IF(F16="yes",1,0)*'Grading Scale'!E$3)+(IF(G16="yes",1,0)*'Grading Scale'!E$4)+(IF(H16="yes",1,0)*'Grading Scale'!E$5)+(IF(I16="yes",1,0)*'Grading Scale'!E$6)+(IF(J16="yes",1,0)*'Grading Scale'!E$7)+(IF(K16="yes",1,0)*'Grading Scale'!E$8)+(IF(L16="yes",1,0)*'Grading Scale'!E$9)+(IF(M16="yes",1,0)*'Grading Scale'!E$10)+(IF(N16="yes",1,0)*'Grading Scale'!E$11)+(IF(O16="yes",1,0)*'Grading Scale'!E$12)+(IF(P16="yes",1,0)*'Grading Scale'!E$13))/'Grading Scale'!E$14*100,0), "") -> 80 | T16: =IF(ISNUMBER(S16),VLOOKUP(S16,'Grading Scale'!$A$2:$B$14, 2), "") -> B−
A17: 42408 | B17: Alaska | C17: Real Estate | D17: =IF(NOT(ISBLANK(C17)), VLOOKUP(C17,'Dataset Descriptions'!$A$2:$B$10, 2, FALSE), "") -> State-owned land and buildings. | E17: unsure | F17: unsure | G17: unsure | H17: unsure | I17: no | J17: unsure | K17: unsure | L17: unsure | M17: unsure | N17: no | O17: unsure | P17: unsure | R17: No such records or references to them can be found, for either land or buildings. | S17: =IF(NOT(ISBLANK(E17)), ROUND(((IF(E17="yes",1,0)*'Grading Scale'!E$2)+(IF(F17="yes",1,0)*'Grading Scale'!E$3)+(IF(G17="yes",1,0)*'Grading Scale'!E$4)+(IF(H17="yes",1,0)*'Grading Scale'!E$5)+(IF(I17="yes",1,0)*'Grading Scale'!E$6)+(IF(J17="yes",1,0)*'Grading Scale'!E$7)+(IF(K17="yes",1,0)*'Grading Scale'!E$8)+(IF(L17="yes",1,0)*'Grading Scale'!E$9)+(IF(M17="yes",1,0)*'Grading Scale'!E$10)+(IF(N17="yes",1,0)*'Grading Scale'!E$11)+(IF(O17="yes",1,0)*'Grading Scale'!E$12)+(IF(P17="yes",1,0)*'Grading Scale'!E$13))/'Grading Scale'!E$14*100,0), "") -> 0 | T17: =IF(ISNUMBER(S17),VLOOKUP(S17,'Grading Scale'!$A$2:$B$14, 2), "") -> F
A18: 42408 | B18: Alaska | C18: Restaurant Inspections | D18: =IF(NOT(ISBLANK(C18)), VLOOKUP(C18,'Dataset Descriptions'!$A$2:$B$10, 2, FALSE), "") -> Health inspections of establishments that serve food to the public. | E18: yes | F18: yes | G18: yes | H18: yes | I18: yes | J18: no | K18: no | L18: yes | M18: yes | N18: no | O18: no | P18: yes | Q18: http://ak.healthinspections.us/alaska/ | R18: These are links to PDFs of reports. | S18: =IF(NOT(ISBLANK(E18)), ROUND(((IF(E18="yes",1,0)*'Grading Scale'!E$2)+(IF(F18="yes",1,0)*'Grading Scale'!E$3)+(IF(G18="yes",1,0)*'Grading Scale'!E$4)+(IF(H18="yes",1,0)*'Grading Scale'!E$5)+(IF(I18="yes",1,0)*'Grading Scale'!E$6)+(IF(J18="yes",1,0)*'Grading Scale'!E$7)+(IF(K18="yes",1,0)*'Grading Scale'!E$8)+(IF(L18="yes",1,0)*'Grading Scale'!E$9)+(IF(M18="yes",1,0)*'Grading Scale'!E$10)+(IF(N18="yes",1,0)*'Grading Scale'!E$11)+(IF(O18="yes",1,0)*'Grading Scale'!E$12)+(IF(P18="yes",1,0)*'Grading Scale'!E$13))/'Grading Scale'!E$14*100,0), "") -> 45 | T18: =IF(ISNUMBER(S18),VLOOKUP(S18,'Grading Scale'!$A$2:$B$14, 2), "") -> F
A19: 42408 | B19: Alaska | C19: Vehicle Crashes | D19: =IF(NOT(ISBLANK(C19)), VLOOKUP(C19,'Dataset Descriptions'!$A$2:$B$10, 2, FALSE), "") -> Incident-level reportable motor vehicle crash records. | E19: yes | F19: yes | G19: yes | H19: yes | I19: yes | J19: no | K19: yes | L19: yes | M19: no | N19: no | O19: no | P19: no | Q19: http://www.dot.alaska.gov/stwdplng/transdata/crash.shtml | R19: These are statistics, not data, and they haven't been updated in 5 years. Alaska has a proper data storage system for crash records, called "Highway Data Port," but the URL where it once lived now generates a 404, and we have been unable to track it down. | S19: =IF(NOT(ISBLANK(E19)), ROUND(((IF(E19="yes",1,0)*'Grading Scale'!E$2)+(IF(F19="yes",1,0)*'Grading Scale'!E$3)+(IF(G19="yes",1,0)*'Grading Scale'!E$4)+(IF(H19="yes",1,0)*'Grading Scale'!E$5)+(IF(I19="yes",1,0)*'Grading Scale'!E$6)+(IF(J19="yes",1,0)*'Grading Scale'!E$7)+(IF(K19="yes",1,0)*'Grading Scale'!E$8)+(IF(L19="yes",1,0)*'Grading Scale'!E$9)+(IF(M19="yes",1,0)*'Grading Scale'!E$10)+(IF(N19="yes",1,0)*'Grading Scale'!E$11)+(IF(O19="yes",1,0)*'Grading Scale'!E$12)+(IF(P19="yes",1,0)*'Grading Scale'!E$13))/'Grading Scale'!E$14*100,0), "") -> 40 | T19: =IF(ISNUMBER(S19),VLOOKUP(S19,'Grading Scale'!$A$2:$B$14, 2), "") -> F
A20: 42338 | B20: Arizona | C20: Address Points | D20: =IF(NOT(ISBLANK(C20)), VLOOKUP(C20,'Dataset Descriptions'!$A$2:$B$10, 2, FALSE), "") -> The geographic coordinates for physical addresses. | E20: no | F20: no | G20: no | H20: no | I20: no | J20: no | K20: no | L20: no | M20: no | N20: no | O20: no | P20: no | S20: =IF(NOT(ISBLANK(E20)), ROUND(((IF(E20="yes",1,0)*'Grading Scale'!E$2)+(IF(F20="yes",1,0)*'Grading Scale'!E$3)+(IF(G20="yes",1,0)*'Grading Scale'!E$4)+(IF(H20="yes",1,0)*'Grading Scale'!E$5)+(IF(I20="yes",1,0)*'Grading Scale'!E$6)+(IF(J20="yes",1,0)*'Grading Scale'!E$7)+(IF(K20="yes",1,0)*'Grading Scale'!E$8)+(IF(L20="yes",1,0)*'Grading Scale'!E$9)+(IF(M20="yes",1,0)*'Grading Scale'!E$10)+(IF(N20="yes",1,0)*'Grading Scale'!E$11)+(IF(O20="yes",1,0)*'Grading Scale'!E$12)+(IF(P20="yes",1,0)*'Grading Scale'!E$13))/'Grading Scale'!E$14*100,0), "") -> 0 | T20: =IF(ISNUMBER(S20),VLOOKUP(S20,'Grading Scale'!$A$2:$B$14, 2), "") -> F
A21: 42374 | B21: Arizona | C21: Checkbook | D21: =IF(NOT(ISBLANK(C21)), VLOOKUP(C21,'Dataset Descriptions'!$A$2:$B$10, 2, FALSE), "") -> Transaction-level, per-agency spending records. | E21: yes | F21: yes | G21: yes | H21: yes | I21: yes | J21: yes | K21: yes | L21: yes | M21: no | N21: no | O21: no | P21: yes | Q21: http://www.azcheckbook.com/ | R21: Data provided as a zipped TSV. It is only updated once annually, in September. | S21: =IF(NOT(ISBLANK(E21)), ROUND(((IF(E21="yes",1,0)*'Grading Scale'!E$2)+(IF(F21="yes",1,0)*'Grading Scale'!E$3)+(IF(G21="yes",1,0)*'Grading Scale'!E$4)+(IF(H21="yes",1,0)*'Grading Scale'!E$5)+(IF(I21="yes",1,0)*'Grading Scale'!E$6)+(IF(J21="yes",1,0)*'Grading Scale'!E$7)+(IF(K21="yes",1,0)*'Grading Scale'!E$8)+(IF(L21="yes",1,0)*'Grading Scale'!E$9)+(IF(M21="yes",1,0)*'Grading Scale'!E$10)+(IF(N21="yes",1,0)*'Grading Scale'!E$11)+(IF(O21="yes",1,0)*'Grading Scale'!E$12)+(IF(P21="yes",1,0)*'Grading Scale'!E$13))/'Grading Scale'!E$14*100,0), "") -> 85 | T21: =IF(ISNUMBER(S21),VLOOKUP(S21,'Grading Scale'!$A$2:$B$14, 2), "") -> B
A22: 42402 | B22: Arizona | C22: Companies | D22: =IF(NOT(ISBLANK(C22)), VLOOKUP(C22,'Dataset Descriptions'!$A$2:$B$10, 2, FALSE), "") -> The register of all corporations that exist in the state. | E22: yes | F22: yes | G22: yes | H22: no | I22: yes | J22: yes | K22: yes | L22: yes | M22: yes | N22: no | O22: no | P22: yes | Q22: http://ecorp.azcc.gov/ | R22: HTML version is free. Actual data costs $1,000. | S22: =IF(NOT(ISBLANK(E22)), ROUND(((IF(E22="yes",1,0)*'Grading Scale'!E$2)+(IF(F22="yes",1,0)*'Grading Scale'!E$3)+(IF(G22="yes",1,0)*'Grading Scale'!E$4)+(IF(H22="yes",1,0)*'Grading Scale'!E$5)+(IF(I22="yes",1,0)*'Grading Scale'!E$6)+(IF(J22="yes",1,0)*'Grading Scale'!E$7)+(IF(K22="yes",1,0)*'Grading Scale'!E$8)+(IF(L22="yes",1,0)*'Grading Scale'!E$9)+(IF(M22="yes",1,0)*'Grading Scale'!E$10)+(IF(N22="yes",1,0)*'Grading Scale'!E$11)+(IF(O22="yes",1,0)*'Grading Scale'!E$12)+(IF(P22="yes",1,0)*'Grading Scale'!E$13))/'Grading Scale'!E$14*100,0), "") -> 75 | T22: =IF(ISNUMBER(S22),VLOOKUP(S22,'Grading Scale'!$A$2:$B$14, 2), "") -> C
A23: 42402 | B23: Arizona | C23: Incarceration | D23: =IF(NOT(ISBLANK(C23)), VLOOKUP(C23,'Dataset Descriptions'!$A$2:$B$10, 2, FALSE), "") -> Per-facility inmate population records. | E23: yes | F23: yes | G23: yes | H23: yes | I23: yes | J23: no | K23: no | L23: no | M23: yes | O23: yes | P23: no | Q23: https://corrections.az.gov/node/452 | R23: Provided as PDFs, generated by Excel. Updated daily. Site uses SSL. | S23: =IF(NOT(ISBLANK(E23)), ROUND(((IF(E23="yes",1,0)*'Grading Scale'!E$2)+(IF(F23="yes",1,0)*'Grading Scale'!E$3)+(IF(G23="yes",1,0)*'Grading Scale'!E$4)+(IF(H23="yes",1,0)*'Grading Scale'!E$5)+(IF(I23="yes",1,0)*'Grading Scale'!E$6)+(IF(J23="yes",1,0)*'Grading Scale'!E$7)+(IF(K23="yes",1,0)*'Grading Scale'!E$8)+(IF(L23="yes",1,0)*'Grading Scale'!E$9)+(IF(M23="yes",1,0)*'Grading Scale'!E$10)+(IF(N23="yes",1,0)*'Grading Scale'!E$11)+(IF(O23="yes",1,0)*'Grading Scale'!E$12)+(IF(P23="yes",1,0)*'Grading Scale'!E$13))/'Grading Scale'!E$14*100,0), "") -> 40 | T23: =IF(ISNUMBER(S23),VLOOKUP(S23,'Grading Scale'!$A$2:$B$14, 2), "") -> F
A24: 42338 | B24: Arizona | C24: Legislation | D24: =IF(NOT(ISBLANK(C24)), VLOOKUP(C24,'Dataset Descriptions'!$A$2:$B$10, 2, FALSE), "") -> Bills before the legislature, and the legislators that comprise it. | E24: yes | F24: yes | G24: yes | H24: yes | I24: yes | J24: no | K24: no | L24: no | M24: yes | N24: no | O24: no | P24: yes | Q24: http://www.azleg.gov/ | S24: =IF(NOT(ISBLANK(E24)), ROUND(((IF(E24="yes",1,0)*'Grading Scale'!E$2)+(IF(F24="yes",1,0)*'Grading Scale'!E$3)+(IF(G24="yes",1,0)*'Grading Scale'!E$4)+(IF(H24="yes",1,0)*'Grading Scale'!E$5)+(IF(I24="yes",1,0)*'Grading Scale'!E$6)+(IF(J24="yes",1,0)*'Grading Scale'!E$7)+(IF(K24="yes",1,0)*'Grading Scale'!E$8)+(IF(L24="yes",1,0)*'Grading Scale'!E$9)+(IF(M24="yes",1,0)*'Grading Scale'!E$10)+(IF(N24="yes",1,0)*'Grading Scale'!E$11)+(IF(O24="yes",1,0)*'Grading Scale'!E$12)+(IF(P24="yes",1,0)*'Grading Scale'!E$13))/'Grading Scale'!E$14*100,0), "") -> 40 | T24: =IF(ISNUMBER(S24),VLOOKUP(S24,'Grading Scale'!$A$2:$B$14, 2), "") -> F
A25: 42402 | B25: Arizona | C25: Population Projections | D25: =IF(NOT(ISBLANK(C25)), VLOOKUP(C25,'Dataset Descriptions'!$A$2:$B$10, 2, FALSE), "") -> Forecasts of municipal-level changes in population over coming years. | E25: yes | F25: yes | G25: yes | H25: yes | I25: yes | J25: yes | K25: yes | L25: yes | M25: yes | N25: no | O25: no | P25: no | Q25: https://population.az.gov/ | R25: No GNIS IDs. | S25: =IF(NOT(ISBLANK(E25)), ROUND(((IF(E25="yes",1,0)*'Grading Scale'!E$2)+(IF(F25="yes",1,0)*'Grading Scale'!E$3)+(IF(G25="yes",1,0)*'Grading Scale'!E$4)+(IF(H25="yes",1,0)*'Grading Scale'!E$5)+(IF(I25="yes",1,0)*'Grading Scale'!E$6)+(IF(J25="yes",1,0)*'Grading Scale'!E$7)+(IF(K25="yes",1,0)*'Grading Scale'!E$8)+(IF(L25="yes",1,0)*'Grading Scale'!E$9)+(IF(M25="yes",1,0)*'Grading Scale'!E$10)+(IF(N25="yes",1,0)*'Grading Scale'!E$11)+(IF(O25="yes",1,0)*'Grading Scale'!E$12)+(IF(P25="yes",1,0)*'Grading Scale'!E$13))/'Grading Scale'!E$14*100,0), "") -> 85 | T25: =IF(ISNUMBER(S25),VLOOKUP(S25,'Grading Scale'!$A$2:$B$14, 2), "") -> B
A26: 42360 | B26: Arizona | C26: Real Estate | D26: =IF(NOT(ISBLANK(C26)), VLOOKUP(C26,'Dataset Descriptions'!$A$2:$B$10, 2, FALSE), "") -> State-owned land and buildings. | E26: no | F26: no | G26: no | H26: no | I26: no | J26: no | K26: no | L26: no | M26: no | N26: no | O26: no | P26: no | S26: =IF(NOT(ISBLANK(E26)), ROUND(((IF(E26="yes",1,0)*'Grading Scale'!E$2)+(IF(F26="yes",1,0)*'Grading Scale'!E$3)+(IF(G26="yes",1,0)*'Grading Scale'!E$4)+(IF(H26="yes",1,0)*'Grading Scale'!E$5)+(IF(I26="yes",1,0)*'Grading Scale'!E$6)+(IF(J26="yes",1,0)*'Grading Scale'!E$7)+(IF(K26="yes",1,0)*'Grading Scale'!E$8)+(IF(L26="yes",1,0)*'Grading Scale'!E$9)+(IF(M26="yes",1,0)*'Grading Scale'!E$10)+(IF(N26="yes",1,0)*'Grading Scale'!E$11)+(IF(O26="yes",1,0)*'Grading Scale'!E$12)+(IF(P26="yes",1,0)*'Grading Scale'!E$13))/'Grading Scale'!E$14*100,0), "") -> 0 | T26: =IF(ISNUMBER(S26),VLOOKUP(S26,'Grading Scale'!$A$2:$B$14, 2), "") -> F
A27: 42338 | B27: Arizona | C27: Restaurant Inspections | D27: =IF(NOT(ISBLANK(C27)), VLOOKUP(C27,'Dataset Descriptions'!$A$2:$B$10, 2, FALSE), "") -> Health inspections of establishments that serve food to the public. | E27: no | F27: no | G27: no | H27: no | I27: no | J27: no | K27: no | L27: no | M27: no | N27: no | O27: no | P27: no | S27: =IF(NOT(ISBLANK(E27)), ROUND(((IF(E27="yes",1,0)*'Grading Scale'!E$2)+(IF(F27="yes",1,0)*'Grading Scale'!E$3)+(IF(G27="yes",1,0)*'Grading Scale'!E$4)+(IF(H27="yes",1,0)*'Grading Scale'!E$5)+(IF(I27="yes",1,0)*'Grading Scale'!E$6)+(IF(J27="yes",1,0)*'Grading Scale'!E$7)+(IF(K27="yes",1,0)*'Grading Scale'!E$8)+(IF(L27="yes",1,0)*'Grading Scale'!E$9)+(IF(M27="yes",1,0)*'Grading Scale'!E$10)+(IF(N27="yes",1,0)*'Grading Scale'!E$11)+(IF(O27="yes",1,0)*'Grading Scale'!E$12)+(IF(P27="yes",1,0)*'Grading Scale'!E$13))/'Grading Scale'!E$14*100,0), "") -> 0 | T27: =IF(ISNUMBER(S27),VLOOKUP(S27,'Grading Scale'!$A$2:$B$14, 2), "") -> F
A28: 42375 | B28: Arizona | C28: Vehicle Crashes | D28: =IF(NOT(ISBLANK(C28)), VLOOKUP(C28,'Dataset Descriptions'!$A$2:$B$10, 2, FALSE), "") -> Incident-level reportable motor vehicle crash records. | E28: yes | F28: yes | G28: yes | H28: yes | I28: yes | J28: no | K28: no | L28: no | M28: yes | N28: no | O28: no | P28: no | Q28: http://azdot.gov/mvd/Statistics/arizona-motor-vehicle-crash-facts | R28: These are statistics, not data. | S28: =IF(NOT(ISBLANK(E28)), ROUND(((IF(E28="yes",1,0)*'Grading Scale'!E$2)+(IF(F28="yes",1,0)*'Grading Scale'!E$3)+(IF(G28="yes",1,0)*'Grading Scale'!E$4)+(IF(H28="yes",1,0)*'Grading Scale'!E$5)+(IF(I28="yes",1,0)*'Grading Scale'!E$6)+(IF(J28="yes",1,0)*'Grading Scale'!E$7)+(IF(K28="yes",1,0)*'Grading Scale'!E$8)+(IF(L28="yes",1,0)*'Grading Scale'!E$9)+(IF(M28="yes",1,0)*'Grading Scale'!E$10)+(IF(N28="yes",1,0)*'Grading Scale'!E$11)+(IF(O28="yes",1,0)*'Grading Scale'!E$12)+(IF(P28="yes",1,0)*'Grading Scale'!E$13))/'Grading Scale'!E$14*100,0), "") -> 35 | T28: =IF(ISNUMBER(S28),VLOOKUP(S28,'Grading Scale'!$A$2:$B$14, 2), "") -> F
A29: 42388 | B29: Arkansas | C29: Address Points | D29: =IF(NOT(ISBLANK(C29)), VLOOKUP(C29,'Dataset Descriptions'!$A$2:$B$10, 2, FALSE), "") -> The geographic coordinates for physical addresses. | E29: yes | F29: yes | G29: yes | H29: yes | I29: yes | J29: yes | K29: yes | L29: yes | M29: yes | N29: no | O29: no | P29: yes | Q29: http://gis.arkansas.gov/?product=situs-address-points | R29: Data is affirmatively placed in the public domain. | S29: =IF(NOT(ISBLANK(E29)), ROUND(((IF(E29="yes",1,0)*'Grading Scale'!E$2)+(IF(F29="yes",1,0)*'Grading Scale'!E$3)+(IF(G29="yes",1,0)*'Grading Scale'!E$4)+(IF(H29="yes",1,0)*'Grading Scale'!E$5)+(IF(I29="yes",1,0)*'Grading Scale'!E$6)+(IF(J29="yes",1,0)*'Grading Scale'!E$7)+(IF(K29="yes",1,0)*'Grading Scale'!E$8)+(IF(L29="yes",1,0)*'Grading Scale'!E$9)+(IF(M29="yes",1,0)*'Grading Scale'!E$10)+(IF(N29="yes",1,0)*'Grading Scale'!E$11)+(IF(O29="yes",1,0)*'Grading Scale'!E$12)+(IF(P29="yes",1,0)*'Grading Scale'!E$13))/'Grading Scale'!E$14*100,0), "") -> 90 | T29: =IF(ISNUMBER(S29),VLOOKUP(S29,'Grading Scale'!$A$2:$B$14, 2), "") -> A−
A30: 42388 | B30: Arkansas | C30: Checkbook | D30: =IF(NOT(ISBLANK(C30)), VLOOKUP(C30,'Dataset Descriptions'!$A$2:$B$10, 2, FALSE), "") -> Transaction-level, per-agency spending records. | E30: yes | F30: yes | G30: yes | H30: yes | I30: yes | J30: yes | K30: no | L30: no | M30: yes | N30: no | O30: yes | P30: no | Q30: https://www.ark.org/dfa/transparency/expenditures.php | R30: Data lacks a description of the purpose of the transaction, as well as a voucher or check number. Provided as CSV and Excel files. | S30: =IF(NOT(ISBLANK(E30)), ROUND(((IF(E30="yes",1,0)*'Grading Scale'!E$2)+(IF(F30="yes",1,0)*'Grading Scale'!E$3)+(IF(G30="yes",1,0)*'Grading Scale'!E$4)+(IF(H30="yes",1,0)*'Grading Scale'!E$5)+(IF(I30="yes",1,0)*'Grading Scale'!E$6)+(IF(J30="yes",1,0)*'Grading Scale'!E$7)+(IF(K30="yes",1,0)*'Grading Scale'!E$8)+(IF(L30="yes",1,0)*'Grading Scale'!E$9)+(IF(M30="yes",1,0)*'Grading Scale'!E$10)+(IF(N30="yes",1,0)*'Grading Scale'!E$11)+(IF(O30="yes",1,0)*'Grading Scale'!E$12)+(IF(P30="yes",1,0)*'Grading Scale'!E$13))/'Grading Scale'!E$14*100,0), "") -> 80 | T30: =IF(ISNUMBER(S30),VLOOKUP(S30,'Grading Scale'!$A$2:$B$14, 2), "") -> B−
A31: 42384 | B31: Arkansas | C31: Companies | D31: =IF(NOT(ISBLANK(C31)), VLOOKUP(C31,'Dataset Descriptions'!$A$2:$B$10, 2, FALSE), "") -> The register of all corporations that exist in the state. | E31: yes | F31: yes | G31: yes | H31: no | I31: yes | J31: yes | K31: yes | L31: no | M31: yes | N31: no | O31: unsure | P31: unsure | Q31: https://www.ark.org/sos/special/index.php | R31: Requires a $95/year account with the Information Network of Arkansas. Data then costs $2,000 / month. This made it impossible to perform a complete evaluation of this dataset. | S31: =IF(NOT(ISBLANK(E31)), ROUND(((IF(E31="yes",1,0)*'Grading Scale'!E$2)+(IF(F31="yes",1,0)*'Grading Scale'!E$3)+(IF(G31="yes",1,0)*'Grading Scale'!E$4)+(IF(H31="yes",1,0)*'Grading Scale'!E$5)+(IF(I31="yes",1,0)*'Grading Scale'!E$6)+(IF(J31="yes",1,0)*'Grading Scale'!E$7)+(IF(K31="yes",1,0)*'Grading Scale'!E$8)+(IF(L31="yes",1,0)*'Grading Scale'!E$9)+(IF(M31="yes",1,0)*'Grading Scale'!E$10)+(IF(N31="yes",1,0)*'Grading Scale'!E$11)+(IF(O31="yes",1,0)*'Grading Scale'!E$12)+(IF(P31="yes",1,0)*'Grading Scale'!E$13))/'Grading Scale'!E$14*100,0), "") -> 65 | T31: =IF(ISNUMBER(S31),VLOOKUP(S31,'Grading Scale'!$A$2:$B$14, 2), "") -> D
A32: 42388 | B32: Arkansas | C32: Incarceration | D32: =IF(NOT(ISBLANK(C32)), VLOOKUP(C32,'Dataset Descriptions'!$A$2:$B$10, 2, FALSE), "") -> Per-facility inmate population records. | E32: no | F32: no | G32: no | H32: no | I32: no | J32: no | K32: no | L32: no | M32: no | N32: no | O32: no | P32: no | R32: If this data exists, it appears that it would be at (http://adc.arkansas.gov/resources/Pages/Reports.aspx). This has various types of data, all as PDFs, but none of it correct for this. Note that they sell bulk data of inmate data (http://adc.arkansas.gov/onlineServices/Pages/dataDownload.aspx), requiring a $95/year account plus 10¢ per record, or $1,903.70 in total. This might make it possible to infer population data. | S32: =IF(NOT(ISBLANK(E32)), ROUND(((IF(E32="yes",1,0)*'Grading Scale'!E$2)+(IF(F32="yes",1,0)*'Grading Scale'!E$3)+(IF(G32="yes",1,0)*'Grading Scale'!E$4)+(IF(H32="yes",1,0)*'Grading Scale'!E$5)+(IF(I32="yes",1,0)*'Grading Scale'!E$6)+(IF(J32="yes",1,0)*'Grading Scale'!E$7)+(IF(K32="yes",1,0)*'Grading Scale'!E$8)+(IF(L32="yes",1,0)*'Grading Scale'!E$9)+(IF(M32="yes",1,0)*'Grading Scale'!E$10)+(IF(N32="yes",1,0)*'Grading Scale'!E$11)+(IF(O32="yes",1,0)*'Grading Scale'!E$12)+(IF(P32="yes",1,0)*'Grading Scale'!E$13))/'Grading Scale'!E$14*100,0), "") -> 0 | T32: =IF(ISNUMBER(S32),VLOOKUP(S32,'Grading Scale'!$A$2:$B$14, 2), "") -> F
A33: 42388 | B33: Arkansas | C33: Legislation | D33: =IF(NOT(ISBLANK(C33)), VLOOKUP(C33,'Dataset Descriptions'!$A$2:$B$10, 2, FALSE), "") -> Bills before the legislature, and the legislators that comprise it. | E33: yes | F33: yes | G33: yes | H33: yes | I33: yes | J33: no | K33: no | L33: yes | M33: yes | N33: no | O33: no | P33: yes | Q33: http://www.arkleg.state.ar.us/ | R33: There are third-party references to Arkansas providing CSV files of some legislative data, but our survey was not able to locate any such data. | S33: =IF(NOT(ISBLANK(E33)), ROUND(((IF(E33="yes",1,0)*'Grading Scale'!E$2)+(IF(F33="yes",1,0)*'Grading Scale'!E$3)+(IF(G33="yes",1,0)*'Grading Scale'!E$4)+(IF(H33="yes",1,0)*'Grading Scale'!E$5)+(IF(I33="yes",1,0)*'Grading Scale'!E$6)+(IF(J33="yes",1,0)*'Grading Scale'!E$7)+(IF(K33="yes",1,0)*'Grading Scale'!E$8)+(IF(L33="yes",1,0)*'Grading Scale'!E$9)+(IF(M33="yes",1,0)*'Grading Scale'!E$10)+(IF(N33="yes",1,0)*'Grading Scale'!E$11)+(IF(O33="yes",1,0)*'Grading Scale'!E$12)+(IF(P33="yes",1,0)*'Grading Scale'!E$13))/'Grading Scale'!E$14*100,0), "") -> 45 | T33: =IF(ISNUMBER(S33),VLOOKUP(S33,'Grading Scale'!$A$2:$B$14, 2), "") -> F
A34: 42395 | B34: Arkansas | C34: Population Projections | D34: =IF(NOT(ISBLANK(C34)), VLOOKUP(C34,'Dataset Descriptions'!$A$2:$B$10, 2, FALSE), "") -> Forecasts of municipal-level changes in population over coming years. | E34: yes | F34: yes | G34: yes | H34: yes | I34: yes | J34: yes | K34: yes | L34: no | M34: yes | N34: no | O34: no | P34: no | Q34: http://iea.ualr.edu/population-estimates-a-projections.html#proj | R34: Provided as an Excel file. Lacks FIPS codes or GNIS IDs identifying localities. | S34: =IF(NOT(ISBLANK(E34)), ROUND(((IF(E34="yes",1,0)*'Grading Scale'!E$2)+(IF(F34="yes",1,0)*'Grading Scale'!E$3)+(IF(G34="yes",1,0)*'Grading Scale'!E$4)+(IF(H34="yes",1,0)*'Grading Scale'!E$5)+(IF(I34="yes",1,0)*'Grading Scale'!E$6)+(IF(J34="yes",1,0)*'Grading Scale'!E$7)+(IF(K34="yes",1,0)*'Grading Scale'!E$8)+(IF(L34="yes",1,0)*'Grading Scale'!E$9)+(IF(M34="yes",1,0)*'Grading Scale'!E$10)+(IF(N34="yes",1,0)*'Grading Scale'!E$11)+(IF(O34="yes",1,0)*'Grading Scale'!E$12)+(IF(P34="yes",1,0)*'Grading Scale'!E$13))/'Grading Scale'!E$14*100,0), "") -> 80 | T34: =IF(ISNUMBER(S34),VLOOKUP(S34,'Grading Scale'!$A$2:$B$14, 2), "") -> B−
A35: 42388 | B35: Arkansas | C35: Real Estate | D35: =IF(NOT(ISBLANK(C35)), VLOOKUP(C35,'Dataset Descriptions'!$A$2:$B$10, 2, FALSE), "") -> State-owned land and buildings. | E35: unsure | F35: unsure | G35: unsure | H35: unsure | I35: no | J35: unsure | K35: unsure | L35: unsure | M35: unsure | N35: no | O35: unsure | P35: unsure | S35: =IF(NOT(ISBLANK(E35)), ROUND(((IF(E35="yes",1,0)*'Grading Scale'!E$2)+(IF(F35="yes",1,0)*'Grading Scale'!E$3)+(IF(G35="yes",1,0)*'Grading Scale'!E$4)+(IF(H35="yes",1,0)*'Grading Scale'!E$5)+(IF(I35="yes",1,0)*'Grading Scale'!E$6)+(IF(J35="yes",1,0)*'Grading Scale'!E$7)+(IF(K35="yes",1,0)*'Grading Scale'!E$8)+(IF(L35="yes",1,0)*'Grading Scale'!E$9)+(IF(M35="yes",1,0)*'Grading Scale'!E$10)+(IF(N35="yes",1,0)*'Grading Scale'!E$11)+(IF(O35="yes",1,0)*'Grading Scale'!E$12)+(IF(P35="yes",1,0)*'Grading Scale'!E$13))/'Grading Scale'!E$14*100,0), "") -> 0 | T35: =IF(ISNUMBER(S35),VLOOKUP(S35,'Grading Scale'!$A$2:$B$14, 2), "") -> F
A36: 42388 | B36: Arkansas | C36: Restaurant Inspections | D36: =IF(NOT(ISBLANK(C36)), VLOOKUP(C36,'Dataset Descriptions'!$A$2:$B$10, 2, FALSE), "") -> Health inspections of establishments that serve food to the public. | E36: no | F36: no | G36: no | H36: no | I36: no | J36: no | K36: no | L36: no | M36: no | N36: no | O36: no | P36: no | R36: Arkansas does not provide this data on a statewide basis, state media reports indicate. | S36: =IF(NOT(ISBLANK(E36)), ROUND(((IF(E36="yes",1,0)*'Grading Scale'!E$2)+(IF(F36="yes",1,0)*'Grading Scale'!E$3)+(IF(G36="yes",1,0)*'Grading Scale'!E$4)+(IF(H36="yes",1,0)*'Grading Scale'!E$5)+(IF(I36="yes",1,0)*'Grading Scale'!E$6)+(IF(J36="yes",1,0)*'Grading Scale'!E$7)+(IF(K36="yes",1,0)*'Grading Scale'!E$8)+(IF(L36="yes",1,0)*'Grading Scale'!E$9)+(IF(M36="yes",1,0)*'Grading Scale'!E$10)+(IF(N36="yes",1,0)*'Grading Scale'!E$11)+(IF(O36="yes",1,0)*'Grading Scale'!E$12)+(IF(P36="yes",1,0)*'Grading Scale'!E$13))/'Grading Scale'!E$14*100,0), "") -> 0 | T36: =IF(ISNUMBER(S36),VLOOKUP(S36,'Grading Scale'!$A$2:$B$14, 2), "") -> F
A37: 42389 | B37: Arkansas | C37: Vehicle Crashes | D37: =IF(NOT(ISBLANK(C37)), VLOOKUP(C37,'Dataset Descriptions'!$A$2:$B$10, 2, FALSE), "") -> Incident-level reportable motor vehicle crash records. | E37: yes | F37: yes | G37: unsure | H37: unsure | I37: no | J37: yes | K37: unsure | L37: unsure | M37: unsure | N37: no | O37: unsure | P37: yes | Q37: http://asp.ark.org/services-and-programs/detail/highway-safety-office | R37: Arkansas participates in NHTSA's State Data System, so they can be known to be producing crash data meeting minimum standards. However, they do not share that data publicly. Instead, they provide only PDFs of overall statistics that, as of this writing, have not been updated in 2 years. | S37: =IF(NOT(ISBLANK(E37)), ROUND(((IF(E37="yes",1,0)*'Grading Scale'!E$2)+(IF(F37="yes",1,0)*'Grading Scale'!E$3)+(IF(G37="yes",1,0)*'Grading Scale'!E$4)+(IF(H37="yes",1,0)*'Grading Scale'!E$5)+(IF(I37="yes",1,0)*'Grading Scale'!E$6)+(IF(J37="yes",1,0)*'Grading Scale'!E$7)+(IF(K37="yes",1,0)*'Grading Scale'!E$8)+(IF(L37="yes",1,0)*'Grading Scale'!E$9)+(IF(M37="yes",1,0)*'Grading Scale'!E$10)+(IF(N37="yes",1,0)*'Grading Scale'!E$11)+(IF(O37="yes",1,0)*'Grading Scale'!E$12)+(IF(P37="yes",1,0)*'Grading Scale'!E$13))/'Grading Scale'!E$14*100,0), "") -> 50 | T37: =IF(ISNUMBER(S37),VLOOKUP(S37,'Grading Scale'!$A$2:$B$14, 2), "") -> F
A38: 42349 | B38: California | C38: Address Points | D38: =IF(NOT(ISBLANK(C38)), VLOOKUP(C38,'Dataset Descriptions'!$A$2:$B$10, 2, FALSE), "") -> The geographic coordinates for physical addresses. | E38: no | F38: no | G38: no | H38: no | I38: no | J38: no | K38: no | L38: no | M38: no | N38: no | O38: no | P38: no | S38: =IF(NOT(ISBLANK(E38)), ROUND(((IF(E38="yes",1,0)*'Grading Scale'!E$2)+(IF(F38="yes",1,0)*'Grading Scale'!E$3)+(IF(G38="yes",1,0)*'Grading Scale'!E$4)+(IF(H38="yes",1,0)*'Grading Scale'!E$5)+(IF(I38="yes",1,0)*'Grading Scale'!E$6)+(IF(J38="yes",1,0)*'Grading Scale'!E$7)+(IF(K38="yes",1,0)*'Grading Scale'!E$8)+(IF(L38="yes",1,0)*'Grading Scale'!E$9)+(IF(M38="yes",1,0)*'Grading Scale'!E$10)+(IF(N38="yes",1,0)*'Grading Scale'!E$11)+(IF(O38="yes",1,0)*'Grading Scale'!E$12)+(IF(P38="yes",1,0)*'Grading Scale'!E$13))/'Grading Scale'!E$14*100,0), "") -> 0 | T38: =IF(ISNUMBER(S38),VLOOKUP(S38,'Grading Scale'!$A$2:$B$14, 2), "") -> F
A39: 42402 | B39: California | C39: Checkbook | D39: =IF(NOT(ISBLANK(C39)), VLOOKUP(C39,'Dataset Descriptions'!$A$2:$B$10, 2, FALSE), "") -> Transaction-level, per-agency spending records. | E39: no | F39: no | G39: no | H39: no | I39: no | J39: no | K39: no | L39: no | M39: no | N39: no | O39: no | P39: no | S39: =IF(NOT(ISBLANK(E39)), ROUND(((IF(E39="yes",1,0)*'Grading Scale'!E$2)+(IF(F39="yes",1,0)*'Grading Scale'!E$3)+(IF(G39="yes",1,0)*'Grading Scale'!E$4)+(IF(H39="yes",1,0)*'Grading Scale'!E$5)+(IF(I39="yes",1,0)*'Grading Scale'!E$6)+(IF(J39="yes",1,0)*'Grading Scale'!E$7)+(IF(K39="yes",1,0)*'Grading Scale'!E$8)+(IF(L39="yes",1,0)*'Grading Scale'!E$9)+(IF(M39="yes",1,0)*'Grading Scale'!E$10)+(IF(N39="yes",1,0)*'Grading Scale'!E$11)+(IF(O39="yes",1,0)*'Grading Scale'!E$12)+(IF(P39="yes",1,0)*'Grading Scale'!E$13))/'Grading Scale'!E$14*100,0), "") -> 0 | T39: =IF(ISNUMBER(S39),VLOOKUP(S39,'Grading Scale'!$A$2:$B$14, 2), "") -> F
A40: 42338 | B40: California | C40: Companies | D40: =IF(NOT(ISBLANK(C40)), VLOOKUP(C40,'Dataset Descriptions'!$A$2:$B$10, 2, FALSE), "") -> The register of all corporations that exist in the state. | E40: yes | F40: yes | G40: yes | H40: yes | I40: yes | J40: no | K40: no | L40: no | M40: yes | N40: yes | O40: no | P40: no | Q40: http://kepler.sos.ca.gov/ | R40: Doesn’t list shares or officers. | S40: =IF(NOT(ISBLANK(E40)), ROUND(((IF(E40="yes",1,0)*'Grading Scale'!E$2)+(IF(F40="yes",1,0)*'Grading Scale'!E$3)+(IF(G40="yes",1,0)*'Grading Scale'!E$4)+(IF(H40="yes",1,0)*'Grading Scale'!E$5)+(IF(I40="yes",1,0)*'Grading Scale'!E$6)+(IF(J40="yes",1,0)*'Grading Scale'!E$7)+(IF(K40="yes",1,0)*'Grading Scale'!E$8)+(IF(L40="yes",1,0)*'Grading Scale'!E$9)+(IF(M40="yes",1,0)*'Grading Scale'!E$10)+(IF(N40="yes",1,0)*'Grading Scale'!E$11)+(IF(O40="yes",1,0)*'Grading Scale'!E$12)+(IF(P40="yes",1,0)*'Grading Scale'!E$13))/'Grading Scale'!E$14*100,0), "") -> 40 | T40: =IF(ISNUMBER(S40),VLOOKUP(S40,'Grading Scale'!$A$2:$B$14, 2), "") -> F
A41: 42360 | B41: California | C41: Incarceration | D41: =IF(NOT(ISBLANK(C41)), VLOOKUP(C41,'Dataset Descriptions'!$A$2:$B$10, 2, FALSE), "") -> Per-facility inmate population records. | E41: yes | F41: yes | G41: yes | H41: yes | I41: yes | J41: no | K41: no | L41: no | M41: yes | N41: no | O41: no | P41: yes | Q41: http://www.cdcr.ca.gov/Reports_Research/Offender_Information_Services_Branch/Offender_Information_Reports.html | S41: =IF(NOT(ISBLANK(E41)), ROUND(((IF(E41="yes",1,0)*'Grading Scale'!E$2)+(IF(F41="yes",1,0)*'Grading Scale'!E$3)+(IF(G41="yes",1,0)*'Grading Scale'!E$4)+(IF(H41="yes",1,0)*'Grading Scale'!E$5)+(IF(I41="yes",1,0)*'Grading Scale'!E$6)+(IF(J41="yes",1,0)*'Grading Scale'!E$7)+(IF(K41="yes",1,0)*'Grading Scale'!E$8)+(IF(L41="yes",1,0)*'Grading Scale'!E$9)+(IF(M41="yes",1,0)*'Grading Scale'!E$10)+(IF(N41="yes",1,0)*'Grading Scale'!E$11)+(IF(O41="yes",1,0)*'Grading Scale'!E$12)+(IF(P41="yes",1,0)*'Grading Scale'!E$13))/'Grading Scale'!E$14*100,0), "") -> 40 | T41: =IF(ISNUMBER(S41),VLOOKUP(S41,'Grading Scale'!$A$2:$B$14, 2), "") -> F
A42: 42338 | B42: California | C42: Legislation | D42: =IF(NOT(ISBLANK(C42)), VLOOKUP(C42,'Dataset Descriptions'!$A$2:$B$10, 2, FALSE), "") -> Bills before the legislature, and the legislators that comprise it. | E42: yes | F42: yes | G42: yes | H42: yes | I42: yes | J42: yes | K42: yes | L42: no | M42: yes | N42: no | O42: no | P42: yes | Q42: ftp://www.leginfo.ca.gov/pub/ | R42: Data is provided as SQL dumps and as TSV at ftp://www.leginfo.ca.gov/pub/bill/pubinfo_Readme.pdf. | S42: =IF(NOT(ISBLANK(E42)), ROUND(((IF(E42="yes",1,0)*'Grading Scale'!E$2)+(IF(F42="yes",1,0)*'Grading Scale'!E$3)+(IF(G42="yes",1,0)*'Grading Scale'!E$4)+(IF(H42="yes",1,0)*'Grading Scale'!E$5)+(IF(I42="yes",1,0)*'Grading Scale'!E$6)+(IF(J42="yes",1,0)*'Grading Scale'!E$7)+(IF(K42="yes",1,0)*'Grading Scale'!E$8)+(IF(L42="yes",1,0)*'Grading Scale'!E$9)+(IF(M42="yes",1,0)*'Grading Scale'!E$10)+(IF(N42="yes",1,0)*'Grading Scale'!E$11)+(IF(O42="yes",1,0)*'Grading Scale'!E$12)+(IF(P42="yes",1,0)*'Grading Scale'!E$13))/'Grading Scale'!E$14*100,0), "") -> 85 | T42: =IF(ISNUMBER(S42),VLOOKUP(S42,'Grading Scale'!$A$2:$B$14, 2), "") -> B
A43: 42338 | B43: California | C43: Population Projections | D43: =IF(NOT(ISBLANK(C43)), VLOOKUP(C43,'Dataset Descriptions'!$A$2:$B$10, 2, FALSE), "") -> Forecasts of municipal-level changes in population over coming years. | E43: yes | F43: yes | G43: yes | H43: yes | I43: yes | J43: yes | K43: yes | L43: no | M43: yes | N43: no | O43: no | P43: yes | Q43: http://www.dof.ca.gov/research/demographic/reports/projections/ | R43: Only Excel files are provided. | S43: =IF(NOT(ISBLANK(E43)), ROUND(((IF(E43="yes",1,0)*'Grading Scale'!E$2)+(IF(F43="yes",1,0)*'Grading Scale'!E$3)+(IF(G43="yes",1,0)*'Grading Scale'!E$4)+(IF(H43="yes",1,0)*'Grading Scale'!E$5)+(IF(I43="yes",1,0)*'Grading Scale'!E$6)+(IF(J43="yes",1,0)*'Grading Scale'!E$7)+(IF(K43="yes",1,0)*'Grading Scale'!E$8)+(IF(L43="yes",1,0)*'Grading Scale'!E$9)+(IF(M43="yes",1,0)*'Grading Scale'!E$10)+(IF(N43="yes",1,0)*'Grading Scale'!E$11)+(IF(O43="yes",1,0)*'Grading Scale'!E$12)+(IF(P43="yes",1,0)*'Grading Scale'!E$13))/'Grading Scale'!E$14*100,0), "") -> 85 | T43: =IF(ISNUMBER(S43),VLOOKUP(S43,'Grading Scale'!$A$2:$B$14, 2), "") -> B
A44: 42338 | B44: California | C44: Real Estate | D44: =IF(NOT(ISBLANK(C44)), VLOOKUP(C44,'Dataset Descriptions'!$A$2:$B$10, 2, FALSE), "") -> State-owned land and buildings. | E44: yes | F44: yes | G44: yes | H44: yes | I44: yes | J44: no | K44: no | L44: yes | M44: unsure | N44: no | O44: no | P44: yes | Q44: http://www.spi.dgs.ca.gov/wscripts/spi.asp?action=Main | S44: =IF(NOT(ISBLANK(E44)), ROUND(((IF(E44="yes",1,0)*'Grading Scale'!E$2)+(IF(F44="yes",1,0)*'Grading Scale'!E$3)+(IF(G44="yes",1,0)*'Grading Scale'!E$4)+(IF(H44="yes",1,0)*'Grading Scale'!E$5)+(IF(I44="yes",1,0)*'Grading Scale'!E$6)+(IF(J44="yes",1,0)*'Grading Scale'!E$7)+(IF(K44="yes",1,0)*'Grading Scale'!E$8)+(IF(L44="yes",1,0)*'Grading Scale'!E$9)+(IF(M44="yes",1,0)*'Grading Scale'!E$10)+(IF(N44="yes",1,0)*'Grading Scale'!E$11)+(IF(O44="yes",1,0)*'Grading Scale'!E$12)+(IF(P44="yes",1,0)*'Grading Scale'!E$13))/'Grading Scale'!E$14*100,0), "") -> 40 | T44: =IF(ISNUMBER(S44),VLOOKUP(S44,'Grading Scale'!$A$2:$B$14, 2), "") -> F
A45: 42402 | B45: California | C45: Restaurant Inspections | D45: =IF(NOT(ISBLANK(C45)), VLOOKUP(C45,'Dataset Descriptions'!$A$2:$B$10, 2, FALSE), "") -> Health inspections of establishments that serve food to the public. | E45: no | F45: no | G45: no | H45: no | I45: no | J45: no | K45: no | L45: yes | M45: no | N45: no | O45: no | P45: no | Q45: http://www.ca.gov/OnlineServices/OS_Consumers_inspections.html | R45: They just link to some counties’ websites. | S45: =IF(NOT(ISBLANK(E45)), ROUND(((IF(E45="yes",1,0)*'Grading Scale'!E$2)+(IF(F45="yes",1,0)*'Grading Scale'!E$3)+(IF(G45="yes",1,0)*'Grading Scale'!E$4)+(IF(H45="yes",1,0)*'Grading Scale'!E$5)+(IF(I45="yes",1,0)*'Grading Scale'!E$6)+(IF(J45="yes",1,0)*'Grading Scale'!E$7)+(IF(K45="yes",1,0)*'Grading Scale'!E$8)+(IF(L45="yes",1,0)*'Grading Scale'!E$9)+(IF(M45="yes",1,0)*'Grading Scale'!E$10)+(IF(N45="yes",1,0)*'Grading Scale'!E$11)+(IF(O45="yes",1,0)*'Grading Scale'!E$12)+(IF(P45="yes",1,0)*'Grading Scale'!E$13))/'Grading Scale'!E$14*100,0), "") -> 5 | T45: =IF(ISNUMBER(S45),VLOOKUP(S45,'Grading Scale'!$A$2:$B$14, 2), "") -> F
A46: 42375 | B46: California | C46: Vehicle Crashes | D46: =IF(NOT(ISBLANK(C46)), VLOOKUP(C46,'Dataset Descriptions'!$A$2:$B$10, 2, FALSE), "") -> Incident-level reportable motor vehicle crash records. | E46: yes | F46: yes | G46: yes | H46: yes | I46: yes | J46: yes | K46: yes | L46: no | M46: no | N46: yes | O46: no | P46: no | Q46: http://www.ots.ca.gov/Media_and_Research/Data_and_Statistics.asp | R46: These are statistics, not data. The most recent data is from 2012. Only Excel files are provided. | S46: =IF(NOT(ISBLANK(E46)), ROUND(((IF(E46="yes",1,0)*'Grading Scale'!E$2)+(IF(F46="yes",1,0)*'Grading Scale'!E$3)+(IF(G46="yes",1,0)*'Grading Scale'!E$4)+(IF(H46="yes",1,0)*'Grading Scale'!E$5)+(IF(I46="yes",1,0)*'Grading Scale'!E$6)+(IF(J46="yes",1,0)*'Grading Scale'!E$7)+(IF(K46="yes",1,0)*'Grading Scale'!E$8)+(IF(L46="yes",1,0)*'Grading Scale'!E$9)+(IF(M46="yes",1,0)*'Grading Scale'!E$10)+(IF(N46="yes",1,0)*'Grading Scale'!E$11)+(IF(O46="yes",1,0)*'Grading Scale'!E$12)+(IF(P46="yes",1,0)*'Grading Scale'!E$13))/'Grading Scale'!E$14*100,0), "") -> 80 | T46: =IF(ISNUMBER(S46),VLOOKUP(S46,'Grading Scale'!$A$2:$B$14, 2), "") -> B−
A47: 42626 | B47: Colorado | C47: Address Points | D47: =IF(NOT(ISBLANK(C47)), VLOOKUP(C47,'Dataset Descriptions'!$A$2:$B$10, 2, FALSE), "") -> The geographic coordinates for physical addresses. | E47: yes | F47: yes | G47: yes | H47: yes | I47: yes | J47: yes | K47: yes | L47: yes | M47: yes | N47: yes | O47: yes | P47: no | Q47: https://data.colorado.gov/Transportation/2015-Colorado-Address-Layer-Public-/n7je-akky | R47: Data is affirmatively placed in the public domain. Verifiable by virtue of being served over HTTPS. This does not include every municipality within Colorado. | S47: =IF(NOT(ISBLANK(E47)), ROUND(((IF(E47="yes",1,0)*'Grading Scale'!E$2)+(IF(F47="yes",1,0)*'Grading Scale'!E$3)+(IF(G47="yes",1,0)*'Grading Scale'!E$4)+(IF(H47="yes",1,0)*'Grading Scale'!E$5)+(IF(I47="yes",1,0)*'Grading Scale'!E$6)+(IF(J47="yes",1,0)*'Grading Scale'!E$7)+(IF(K47="yes",1,0)*'Grading Scale'!E$8)+(IF(L47="yes",1,0)*'Grading Scale'!E$9)+(IF(M47="yes",1,0)*'Grading Scale'!E$10)+(IF(N47="yes",1,0)*'Grading Scale'!E$11)+(IF(O47="yes",1,0)*'Grading Scale'!E$12)+(IF(P47="yes",1,0)*'Grading Scale'!E$13))/'Grading Scale'!E$14*100,0), "") -> 95 | T47: =IF(ISNUMBER(S47),VLOOKUP(S47,'Grading Scale'!$A$2:$B$14, 2), "") -> A
A48: 42347 | B48: Colorado | C48: Checkbook | D48: =IF(NOT(ISBLANK(C48)), VLOOKUP(C48,'Dataset Descriptions'!$A$2:$B$10, 2, FALSE), "") -> Transaction-level, per-agency spending records. | E48: yes | F48: yes | G48: yes | H48: yes | I48: yes | J48: yes | K48: no | L48: yes | M48: yes | N48: no | O48: yes | P48: yes | Q48: https://www.colorado.gov/apps/oit/transparency/ | R48: Data verifiable by being served over HTTPS. Data can only be exported (as CSV) at the conclusion of an interactive process, which only allows a small slice of data to be transferred. | S48: =IF(NOT(ISBLANK(E48)), ROUND(((IF(E48="yes",1,0)*'Grading Scale'!E$2)+(IF(F48="yes",1,0)*'Grading Scale'!E$3)+(IF(G48="yes",1,0)*'Grading Scale'!E$4)+(IF(H48="yes",1,0)*'Grading Scale'!E$5)+(IF(I48="yes",1,0)*'Grading Scale'!E$6)+(IF(J48="yes",1,0)*'Grading Scale'!E$7)+(IF(K48="yes",1,0)*'Grading Scale'!E$8)+(IF(L48="yes",1,0)*'Grading Scale'!E$9)+(IF(M48="yes",1,0)*'Grading Scale'!E$10)+(IF(N48="yes",1,0)*'Grading Scale'!E$11)+(IF(O48="yes",1,0)*'Grading Scale'!E$12)+(IF(P48="yes",1,0)*'Grading Scale'!E$13))/'Grading Scale'!E$14*100,0), "") -> 90 | T48: =IF(ISNUMBER(S48),VLOOKUP(S48,'Grading Scale'!$A$2:$B$14, 2), "") -> A−
A49: 42347 | B49: Colorado | C49: Companies | D49: =IF(NOT(ISBLANK(C49)), VLOOKUP(C49,'Dataset Descriptions'!$A$2:$B$10, 2, FALSE), "") -> The register of all corporations that exist in the state. | E49: yes | F49: yes | G49: yes | H49: yes | I49: yes | J49: yes | K49: yes | L49: yes | M49: yes | N49: yes | O49: yes | P49: yes | Q49: https://data.colorado.gov/Business/Colorado-Business-Entities/4ykn-tg5h | S49: =IF(NOT(ISBLANK(E49)), ROUND(((IF(E49="yes",1,0)*'Grading Scale'!E$2)+(IF(F49="yes",1,0)*'Grading Scale'!E$3)+(IF(G49="yes",1,0)*'Grading Scale'!E$4)+(IF(H49="yes",1,0)*'Grading Scale'!E$5)+(IF(I49="yes",1,0)*'Grading Scale'!E$6)+(IF(J49="yes",1,0)*'Grading Scale'!E$7)+(IF(K49="yes",1,0)*'Grading Scale'!E$8)+(IF(L49="yes",1,0)*'Grading Scale'!E$9)+(IF(M49="yes",1,0)*'Grading Scale'!E$10)+(IF(N49="yes",1,0)*'Grading Scale'!E$11)+(IF(O49="yes",1,0)*'Grading Scale'!E$12)+(IF(P49="yes",1,0)*'Grading Scale'!E$13))/'Grading Scale'!E$14*100,0), "") -> 100 | T49: =IF(ISNUMBER(S49),VLOOKUP(S49,'Grading Scale'!$A$2:$B$14, 2), "") -> A+
A50: 42347 | B50: Colorado | C50: Incarceration | D50: =IF(NOT(ISBLANK(C50)), VLOOKUP(C50,'Dataset Descriptions'!$A$2:$B$10, 2, FALSE), "") -> Per-facility inmate population records. | E50: yes | F50: yes | G50: yes | H50: yes | I50: yes | J50: no | K50: no | L50: no | M50: yes | N50: no | O50: yes | P50: no | Q50: https://www.colorado.gov/pacific/dcj-ors/ors-corrpops | R50: These are statistics, not data. Updated quarterly. | S50: =IF(NOT(ISBLANK(E50)), ROUND(((IF(E50="yes",1,0)*'Grading Scale'!E$2)+(IF(F50="yes",1,0)*'Grading Scale'!E$3)+(IF(G50="yes",1,0)*'Grading Scale'!E$4)+(IF(H50="yes",1,0)*'Grading Scale'!E$5)+(IF(I50="yes",1,0)*'Grading Scale'!E$6)+(IF(J50="yes",1,0)*'Grading Scale'!E$7)+(IF(K50="yes",1,0)*'Grading Scale'!E$8)+(IF(L50="yes",1,0)*'Grading Scale'!E$9)+(IF(M50="yes",1,0)*'Grading Scale'!E$10)+(IF(N50="yes",1,0)*'Grading Scale'!E$11)+(IF(O50="yes",1,0)*'Grading Scale'!E$12)+(IF(P50="yes",1,0)*'Grading Scale'!E$13))/'Grading Scale'!E$14*100,0), "") -> 40 | T50: =IF(ISNUMBER(S50),VLOOKUP(S50,'Grading Scale'!$A$2:$B$14, 2), "") -> F
A51: 42347 | B51: Colorado | C51: Legislation | D51: =IF(NOT(ISBLANK(C51)), VLOOKUP(C51,'Dataset Descriptions'!$A$2:$B$10, 2, FALSE), "") -> Bills before the legislature, and the legislators that comprise it. | E51: yes | F51: yes | G51: yes | H51: yes | I51: yes | J51: no | K51: no | L51: yes | M51: yes | N51: no | O51: no | P51: yes | Q51: http://www.leg.state.co.us/ | R51: Most information is only available as PDFs. | S51: =IF(NOT(ISBLANK(E51)), ROUND(((IF(E51="yes",1,0)*'Grading Scale'!E$2)+(IF(F51="yes",1,0)*'Grading Scale'!E$3)+(IF(G51="yes",1,0)*'Grading Scale'!E$4)+(IF(H51="yes",1,0)*'Grading Scale'!E$5)+(IF(I51="yes",1,0)*'Grading Scale'!E$6)+(IF(J51="yes",1,0)*'Grading Scale'!E$7)+(IF(K51="yes",1,0)*'Grading Scale'!E$8)+(IF(L51="yes",1,0)*'Grading Scale'!E$9)+(IF(M51="yes",1,0)*'Grading Scale'!E$10)+(IF(N51="yes",1,0)*'Grading Scale'!E$11)+(IF(O51="yes",1,0)*'Grading Scale'!E$12)+(IF(P51="yes",1,0)*'Grading Scale'!E$13))/'Grading Scale'!E$14*100,0), "") -> 45 | T51: =IF(ISNUMBER(S51),VLOOKUP(S51,'Grading Scale'!$A$2:$B$14, 2), "") -> F
A52: 42347 | B52: Colorado | C52: Population Projections | D52: =IF(NOT(ISBLANK(C52)), VLOOKUP(C52,'Dataset Descriptions'!$A$2:$B$10, 2, FALSE), "") -> Forecasts of municipal-level changes in population over coming years. | E52: yes | F52: yes | G52: yes | H52: yes | I52: yes | J52: yes | K52: yes | L52: yes | M52: yes | N52: yes | O52: yes | P52: yes | Q52: https://data.colorado.gov/Demographics/Colorado-Population-Projections/q5vp-adf3 | S52: =IF(NOT(ISBLANK(E52)), ROUND(((IF(E52="yes",1,0)*'Grading Scale'!E$2)+(IF(F52="yes",1,0)*'Grading Scale'!E$3)+(IF(G52="yes",1,0)*'Grading Scale'!E$4)+(IF(H52="yes",1,0)*'Grading Scale'!E$5)+(IF(I52="yes",1,0)*'Grading Scale'!E$6)+(IF(J52="yes",1,0)*'Grading Scale'!E$7)+(IF(K52="yes",1,0)*'Grading Scale'!E$8)+(IF(L52="yes",1,0)*'Grading Scale'!E$9)+(IF(M52="yes",1,0)*'Grading Scale'!E$10)+(IF(N52="yes",1,0)*'Grading Scale'!E$11)+(IF(O52="yes",1,0)*'Grading Scale'!E$12)+(IF(P52="yes",1,0)*'Grading Scale'!E$13))/'Grading Scale'!E$14*100,0), "") -> 100 | T52: =IF(ISNUMBER(S52),VLOOKUP(S52,'Grading Scale'!$A$2:$B$14, 2), "") -> A+
A53: 42347 | B53: Colorado | C53: Real Estate | D53: =IF(NOT(ISBLANK(C53)), VLOOKUP(C53,'Dataset Descriptions'!$A$2:$B$10, 2, FALSE), "") -> State-owned land and buildings. | E53: unsure | F53: unsure | G53: unsure | H53: unsure | I53: no | J53: unsure | K53: no | L53: unsure | M53: unsure | N53: no | O53: no | P53: unsure | S53: =IF(NOT(ISBLANK(E53)), ROUND(((IF(E53="yes",1,0)*'Grading Scale'!E$2)+(IF(F53="yes",1,0)*'Grading Scale'!E$3)+(IF(G53="yes",1,0)*'Grading Scale'!E$4)+(IF(H53="yes",1,0)*'Grading Scale'!E$5)+(IF(I53="yes",1,0)*'Grading Scale'!E$6)+(IF(J53="yes",1,0)*'Grading Scale'!E$7)+(IF(K53="yes",1,0)*'Grading Scale'!E$8)+(IF(L53="yes",1,0)*'Grading Scale'!E$9)+(IF(M53="yes",1,0)*'Grading Scale'!E$10)+(IF(N53="yes",1,0)*'Grading Scale'!E$11)+(IF(O53="yes",1,0)*'Grading Scale'!E$12)+(IF(P53="yes",1,0)*'Grading Scale'!E$13))/'Grading Scale'!E$14*100,0), "") -> 0 | T53: =IF(ISNUMBER(S53),VLOOKUP(S53,'Grading Scale'!$A$2:$B$14, 2), "") -> F
A54: 42347 | B54: Colorado | C54: Restaurant Inspections | D54: =IF(NOT(ISBLANK(C54)), VLOOKUP(C54,'Dataset Descriptions'!$A$2:$B$10, 2, FALSE), "") -> Health inspections of establishments that serve food to the public. | E54: unsure | F54: unsure | G54: unsure | H54: unsure | I54: no | J54: unsure | K54: no | L54: unsure | M54: unsure | N54: no | O54: no | P54: unsure | Q54: https://www.colorado.gov/pacific/cdphe/foodborne-illness-outbreaks | R54: The state is only responsible for inspecting restaurants in Garfield, Grand, Gunnison, Jackson and Moffat counties, but they provide data for none of those counties, nor do they aggregate data for other cities or states. | S54: =IF(NOT(ISBLANK(E54)), ROUND(((IF(E54="yes",1,0)*'Grading Scale'!E$2)+(IF(F54="yes",1,0)*'Grading Scale'!E$3)+(IF(G54="yes",1,0)*'Grading Scale'!E$4)+(IF(H54="yes",1,0)*'Grading Scale'!E$5)+(IF(I54="yes",1,0)*'Grading Scale'!E$6)+(IF(J54="yes",1,0)*'Grading Scale'!E$7)+(IF(K54="yes",1,0)*'Grading Scale'!E$8)+(IF(L54="yes",1,0)*'Grading Scale'!E$9)+(IF(M54="yes",1,0)*'Grading Scale'!E$10)+(IF(N54="yes",1,0)*'Grading Scale'!E$11)+(IF(O54="yes",1,0)*'Grading Scale'!E$12)+(IF(P54="yes",1,0)*'Grading Scale'!E$13))/'Grading Scale'!E$14*100,0), "") -> 0 | T54: =IF(ISNUMBER(S54),VLOOKUP(S54,'Grading Scale'!$A$2:$B$14, 2), "") -> F
A55: 42348 | B55: Colorado | C55: Vehicle Crashes | D55: =IF(NOT(ISBLANK(C55)), VLOOKUP(C55,'Dataset Descriptions'!$A$2:$B$10, 2, FALSE), "") -> Incident-level reportable motor vehicle crash records. | E55: yes | F55: yes | G55: yes | H55: yes | I55: yes | J55: no | K55: no | L55: yes | M55: no | N55: no | O55: yes | P55: no | Q55: https://www.codot.gov/library/traffic/safety-crash-data/accident-rates-books-coding/crash-summary-books/2012-crash-book/view | R55: These are statistics, not data. Data is from 2012. | S55: =IF(NOT(ISBLANK(E55)), ROUND(((IF(E55="yes",1,0)*'Grading Scale'!E$2)+(IF(F55="yes",1,0)*'Grading Scale'!E$3)+(IF(G55="yes",1,0)*'Grading Scale'!E$4)+(IF(H55="yes",1,0)*'Grading Scale'!E$5)+(IF(I55="yes",1,0)*'Grading Scale'!E$6)+(IF(J55="yes",1,0)*'Grading Scale'!E$7)+(IF(K55="yes",1,0)*'Grading Scale'!E$8)+(IF(L55="yes",1,0)*'Grading Scale'!E$9)+(IF(M55="yes",1,0)*'Grading Scale'!E$10)+(IF(N55="yes",1,0)*'Grading Scale'!E$11)+(IF(O55="yes",1,0)*'Grading Scale'!E$12)+(IF(P55="yes",1,0)*'Grading Scale'!E$13))/'Grading Scale'!E$14*100,0), "") -> 40 | T55: =IF(ISNUMBER(S55),VLOOKUP(S55,'Grading Scale'!$A$2:$B$14, 2), "") -> F
A56: 42338 | B56: Connecticut | C56: Address Points | D56: =IF(NOT(ISBLANK(C56)), VLOOKUP(C56,'Dataset Descriptions'!$A$2:$B$10, 2, FALSE), "") -> The geographic coordinates for physical addresses. | E56: yes | F56: yes | G56: yes | H56: yes | I56: yes | J56: yes | K56: yes | L56: yes | M56: yes | N56: yes | O56: yes | P56: no | Q56: https://data.ct.gov/dataset/Address-Points-Preliminary-File/35bv-xa6i | R56: Data is available as a zipped Esri FGDB file or as a RESTful (ArcGIS) endpoint. Connecticut aggregates localities' data, but only a handful of localities are publishing data, so this data is nowhere near complete. | S56: =IF(NOT(ISBLANK(E56)), ROUND(((IF(E56="yes",1,0)*'Grading Scale'!E$2)+(IF(F56="yes",1,0)*'Grading Scale'!E$3)+(IF(G56="yes",1,0)*'Grading Scale'!E$4)+(IF(H56="yes",1,0)*'Grading Scale'!E$5)+(IF(I56="yes",1,0)*'Grading Scale'!E$6)+(IF(J56="yes",1,0)*'Grading Scale'!E$7)+(IF(K56="yes",1,0)*'Grading Scale'!E$8)+(IF(L56="yes",1,0)*'Grading Scale'!E$9)+(IF(M56="yes",1,0)*'Grading Scale'!E$10)+(IF(N56="yes",1,0)*'Grading Scale'!E$11)+(IF(O56="yes",1,0)*'Grading Scale'!E$12)+(IF(P56="yes",1,0)*'Grading Scale'!E$13))/'Grading Scale'!E$14*100,0), "") -> 95 | T56: =IF(ISNUMBER(S56),VLOOKUP(S56,'Grading Scale'!$A$2:$B$14, 2), "") -> A
A57: 42355 | B57: Connecticut | C57: Checkbook | D57: =IF(NOT(ISBLANK(C57)), VLOOKUP(C57,'Dataset Descriptions'!$A$2:$B$10, 2, FALSE), "") -> Transaction-level, per-agency spending records. | E57: yes | F57: yes | G57: yes | H57: yes | I57: yes | J57: yes | K57: yes | L57: yes | M57: yes | N57: yes | O57: yes | P57: no | Q57: https://data.ct.gov/dataset/State-of-CT-Open-Expenditures-Ledger/4b3c-3g3a | R57: At the time that this dataset was surveyed, there were no descriptions of the purpose of each expense (there is a "Description" field, but it was blank for all records), making it incomplete. | S57: =IF(NOT(ISBLANK(E57)), ROUND(((IF(E57="yes",1,0)*'Grading Scale'!E$2)+(IF(F57="yes",1,0)*'Grading Scale'!E$3)+(IF(G57="yes",1,0)*'Grading Scale'!E$4)+(IF(H57="yes",1,0)*'Grading Scale'!E$5)+(IF(I57="yes",1,0)*'Grading Scale'!E$6)+(IF(J57="yes",1,0)*'Grading Scale'!E$7)+(IF(K57="yes",1,0)*'Grading Scale'!E$8)+(IF(L57="yes",1,0)*'Grading Scale'!E$9)+(IF(M57="yes",1,0)*'Grading Scale'!E$10)+(IF(N57="yes",1,0)*'Grading Scale'!E$11)+(IF(O57="yes",1,0)*'Grading Scale'!E$12)+(IF(P57="yes",1,0)*'Grading Scale'!E$13))/'Grading Scale'!E$14*100,0), "") -> 95 | T57: =IF(ISNUMBER(S57),VLOOKUP(S57,'Grading Scale'!$A$2:$B$14, 2), "") -> A
A58: 42338 | B58: Connecticut | C58: Companies | D58: =IF(NOT(ISBLANK(C58)), VLOOKUP(C58,'Dataset Descriptions'!$A$2:$B$10, 2, FALSE), "") -> The register of all corporations that exist in the state. | E58: yes | F58: yes | G58: yes | H58: yes | I58: yes | J58: no | K58: no | L58: no | M58: yes | N58: yes | O58: no | P58: yes | Q58: http://www.concord-sots.ct.gov/CONCORD/ | S58: =IF(NOT(ISBLANK(E58)), ROUND(((IF(E58="yes",1,0)*'Grading Scale'!E$2)+(IF(F58="yes",1,0)*'Grading Scale'!E$3)+(IF(G58="yes",1,0)*'Grading Scale'!E$4)+(IF(H58="yes",1,0)*'Grading Scale'!E$5)+(IF(I58="yes",1,0)*'Grading Scale'!E$6)+(IF(J58="yes",1,0)*'Grading Scale'!E$7)+(IF(K58="yes",1,0)*'Grading Scale'!E$8)+(IF(L58="yes",1,0)*'Grading Scale'!E$9)+(IF(M58="yes",1,0)*'Grading Scale'!E$10)+(IF(N58="yes",1,0)*'Grading Scale'!E$11)+(IF(O58="yes",1,0)*'Grading Scale'!E$12)+(IF(P58="yes",1,0)*'Grading Scale'!E$13))/'Grading Scale'!E$14*100,0), "") -> 45 | T58: =IF(ISNUMBER(S58),VLOOKUP(S58,'Grading Scale'!$A$2:$B$14, 2), "") -> F
A59: 42447 | B59: Connecticut | C59: Incarceration | D59: =IF(NOT(ISBLANK(C59)), VLOOKUP(C59,'Dataset Descriptions'!$A$2:$B$10, 2, FALSE), "") -> Per-facility inmate population records. | E59: yes | F59: yes | G59: yes | H59: yes | I59: yes | J59: yes | K59: yes | L59: yes | M59: yes | N59: yes | O59: yes | P59: yes | Q59: https://data.ct.gov/Public-Safety/Correctional-Facility-Daily-Population-Count-By-Fa/n8x6-s299 | R59: Data is verifiable by virtue of being provided via HTTPS. Although the linked-to dataset is incomplete, because it lacks facility capacity data, Connecticut provides this in another dataset, at (https://data.ct.gov/Public-Safety/Department-of-Corrections-Quarterly-Average-Facilt/f8ar-pgu4). | S59: =IF(NOT(ISBLANK(E59)), ROUND(((IF(E59="yes",1,0)*'Grading Scale'!E$2)+(IF(F59="yes",1,0)*'Grading Scale'!E$3)+(IF(G59="yes",1,0)*'Grading Scale'!E$4)+(IF(H59="yes",1,0)*'Grading Scale'!E$5)+(IF(I59="yes",1,0)*'Grading Scale'!E$6)+(IF(J59="yes",1,0)*'Grading Scale'!E$7)+(IF(K59="yes",1,0)*'Grading Scale'!E$8)+(IF(L59="yes",1,0)*'Grading Scale'!E$9)+(IF(M59="yes",1,0)*'Grading Scale'!E$10)+(IF(N59="yes",1,0)*'Grading Scale'!E$11)+(IF(O59="yes",1,0)*'Grading Scale'!E$12)+(IF(P59="yes",1,0)*'Grading Scale'!E$13))/'Grading Scale'!E$14*100,0), "") -> 100 | T59: =IF(ISNUMBER(S59),VLOOKUP(S59,'Grading Scale'!$A$2:$B$14, 2), "") -> A+
A60: 42338 | B60: Connecticut | C60: Legislation | D60: =IF(NOT(ISBLANK(C60)), VLOOKUP(C60,'Dataset Descriptions'!$A$2:$B$10, 2, FALSE), "") -> Bills before the legislature, and the legislators that comprise it. | E60: yes | F60: yes | G60: yes | H60: yes | I60: yes | J60: yes | K60: yes | L60: no | M60: yes | N60: yes | O60: yes | P60: yes | Q60: https://www.cga.ct.gov/asp/menu/legdownload.asp | S60: =IF(NOT(ISBLANK(E60)), ROUND(((IF(E60="yes",1,0)*'Grading Scale'!E$2)+(IF(F60="yes",1,0)*'Grading Scale'!E$3)+(IF(G60="yes",1,0)*'Grading Scale'!E$4)+(IF(H60="yes",1,0)*'Grading Scale'!E$5)+(IF(I60="yes",1,0)*'Grading Scale'!E$6)+(IF(J60="yes",1,0)*'Grading Scale'!E$7)+(IF(K60="yes",1,0)*'Grading Scale'!E$8)+(IF(L60="yes",1,0)*'Grading Scale'!E$9)+(IF(M60="yes",1,0)*'Grading Scale'!E$10)+(IF(N60="yes",1,0)*'Grading Scale'!E$11)+(IF(O60="yes",1,0)*'Grading Scale'!E$12)+(IF(P60="yes",1,0)*'Grading Scale'!E$13))/'Grading Scale'!E$14*100,0), "") -> 95 | T60: =IF(ISNUMBER(S60),VLOOKUP(S60,'Grading Scale'!$A$2:$B$14, 2), "") -> A
A61: 42355 | B61: Connecticut | C61: Population Projections | D61: =IF(NOT(ISBLANK(C61)), VLOOKUP(C61,'Dataset Descriptions'!$A$2:$B$10, 2, FALSE), "") -> Forecasts of municipal-level changes in population over coming years. | E61: yes | F61: yes | G61: yes | H61: yes | I61: yes | J61: yes | K61: yes | L61: yes | M61: yes | N61: yes | O61: yes | P61: yes | Q61: https://data.ct.gov/Government/Connecticut-Town-Population-Projections-2015-2025/mze8-865g | S61: =IF(NOT(ISBLANK(E61)), ROUND(((IF(E61="yes",1,0)*'Grading Scale'!E$2)+(IF(F61="yes",1,0)*'Grading Scale'!E$3)+(IF(G61="yes",1,0)*'Grading Scale'!E$4)+(IF(H61="yes",1,0)*'Grading Scale'!E$5)+(IF(I61="yes",1,0)*'Grading Scale'!E$6)+(IF(J61="yes",1,0)*'Grading Scale'!E$7)+(IF(K61="yes",1,0)*'Grading Scale'!E$8)+(IF(L61="yes",1,0)*'Grading Scale'!E$9)+(IF(M61="yes",1,0)*'Grading Scale'!E$10)+(IF(N61="yes",1,0)*'Grading Scale'!E$11)+(IF(O61="yes",1,0)*'Grading Scale'!E$12)+(IF(P61="yes",1,0)*'Grading Scale'!E$13))/'Grading Scale'!E$14*100,0), "") -> 100 | T61: =IF(ISNUMBER(S61),VLOOKUP(S61,'Grading Scale'!$A$2:$B$14, 2), "") -> A+
A62: 42355 | B62: Connecticut | C62: Real Estate | D62: =IF(NOT(ISBLANK(C62)), VLOOKUP(C62,'Dataset Descriptions'!$A$2:$B$10, 2, FALSE), "") -> State-owned land and buildings. | E62: yes | F62: yes | G62: yes | H62: yes | I62: yes | J62: yes | K62: yes | L62: yes | M62: yes | N62: yes | O62: yes | P62: yes | Q62: https://data.ct.gov/Government/State-Owned-Buildings/r8ci-yhcn | R62: This includes buildings—land records are found at https://data.ct.gov/Government/State-Owned-Lands/meyk-xprb. | S62: =IF(NOT(ISBLANK(E62)), ROUND(((IF(E62="yes",1,0)*'Grading Scale'!E$2)+(IF(F62="yes",1,0)*'Grading Scale'!E$3)+(IF(G62="yes",1,0)*'Grading Scale'!E$4)+(IF(H62="yes",1,0)*'Grading Scale'!E$5)+(IF(I62="yes",1,0)*'Grading Scale'!E$6)+(IF(J62="yes",1,0)*'Grading Scale'!E$7)+(IF(K62="yes",1,0)*'Grading Scale'!E$8)+(IF(L62="yes",1,0)*'Grading Scale'!E$9)+(IF(M62="yes",1,0)*'Grading Scale'!E$10)+(IF(N62="yes",1,0)*'Grading Scale'!E$11)+(IF(O62="yes",1,0)*'Grading Scale'!E$12)+(IF(P62="yes",1,0)*'Grading Scale'!E$13))/'Grading Scale'!E$14*100,0), "") -> 100 | T62: =IF(ISNUMBER(S62),VLOOKUP(S62,'Grading Scale'!$A$2:$B$14, 2), "") -> A+
A63: 42387 | B63: Connecticut | C63: Restaurant Inspections | D63: =IF(NOT(ISBLANK(C63)), VLOOKUP(C63,'Dataset Descriptions'!$A$2:$B$10, 2, FALSE), "") -> Health inspections of establishments that serve food to the public. | E63: yes | F63: yes | G63: yes | H63: yes | I63: yes | J63: no | K63: no | L63: yes | M63: yes | N63: yes | O63: yes | P63: no | Q63: http://opendatact.github.io/ct_restaurant_inspections/ | R63: Connecticut does not aggregate this data on a statewide basis, but they have set up an interface to access inspection data from localities' websites. The site includes no data, just links to the data. | S63: =IF(NOT(ISBLANK(E63)), ROUND(((IF(E63="yes",1,0)*'Grading Scale'!E$2)+(IF(F63="yes",1,0)*'Grading Scale'!E$3)+(IF(G63="yes",1,0)*'Grading Scale'!E$4)+(IF(H63="yes",1,0)*'Grading Scale'!E$5)+(IF(I63="yes",1,0)*'Grading Scale'!E$6)+(IF(J63="yes",1,0)*'Grading Scale'!E$7)+(IF(K63="yes",1,0)*'Grading Scale'!E$8)+(IF(L63="yes",1,0)*'Grading Scale'!E$9)+(IF(M63="yes",1,0)*'Grading Scale'!E$10)+(IF(N63="yes",1,0)*'Grading Scale'!E$11)+(IF(O63="yes",1,0)*'Grading Scale'!E$12)+(IF(P63="yes",1,0)*'Grading Scale'!E$13))/'Grading Scale'!E$14*100,0), "") -> 50 | T63: =IF(ISNUMBER(S63),VLOOKUP(S63,'Grading Scale'!$A$2:$B$14, 2), "") -> F
A64: 42338 | B64: Connecticut | C64: Vehicle Crashes | D64: =IF(NOT(ISBLANK(C64)), VLOOKUP(C64,'Dataset Descriptions'!$A$2:$B$10, 2, FALSE), "") -> Incident-level reportable motor vehicle crash records. | E64: yes | F64: yes | G64: yes | H64: yes | I64: yes | J64: yes | K64: no | L64: yes | M64: no | N64: yes | O64: no | P64: no | Q64: http://www.ctcrash.uconn.edu/ | R64: Some parts of the site have data only through 2011, while others have data from one year ago. CSV is available, but it requires registering for an account, stepping through a report-generation process, exporting CSV, which is provided via an emailed link. | S64: =IF(NOT(ISBLANK(E64)), ROUND(((IF(E64="yes",1,0)*'Grading Scale'!E$2)+(IF(F64="yes",1,0)*'Grading Scale'!E$3)+(IF(G64="yes",1,0)*'Grading Scale'!E$4)+(IF(H64="yes",1,0)*'Grading Scale'!E$5)+(IF(I64="yes",1,0)*'Grading Scale'!E$6)+(IF(J64="yes",1,0)*'Grading Scale'!E$7)+(IF(K64="yes",1,0)*'Grading Scale'!E$8)+(IF(L64="yes",1,0)*'Grading Scale'!E$9)+(IF(M64="yes",1,0)*'Grading Scale'!E$10)+(IF(N64="yes",1,0)*'Grading Scale'!E$11)+(IF(O64="yes",1,0)*'Grading Scale'!E$12)+(IF(P64="yes",1,0)*'Grading Scale'!E$13))/'Grading Scale'!E$14*100,0), "") -> 80 | T64: =IF(ISNUMBER(S64),VLOOKUP(S64,'Grading Scale'!$A$2:$B$14, 2), "") -> B−
A65: 42405 | B65: Delaware | C65: Address Points | D65: =IF(NOT(ISBLANK(C65)), VLOOKUP(C65,'Dataset Descriptions'!$A$2:$B$10, 2, FALSE), "") -> The geographic coordinates for physical addresses. | E65: yes | F65: yes | G65: unsure | H65: unsure | I65: no | J65: yes | K65: unsure | L65: unsure | M65: unsure | N65: no | O65: unsure | P65: yes | R65: Agency documentation shows that this dataset exists, but it is nowhere to be found. We have contacted them for further information. | S65: =IF(NOT(ISBLANK(E65)), ROUND(((IF(E65="yes",1,0)*'Grading Scale'!E$2)+(IF(F65="yes",1,0)*'Grading Scale'!E$3)+(IF(G65="yes",1,0)*'Grading Scale'!E$4)+(IF(H65="yes",1,0)*'Grading Scale'!E$5)+(IF(I65="yes",1,0)*'Grading Scale'!E$6)+(IF(J65="yes",1,0)*'Grading Scale'!E$7)+(IF(K65="yes",1,0)*'Grading Scale'!E$8)+(IF(L65="yes",1,0)*'Grading Scale'!E$9)+(IF(M65="yes",1,0)*'Grading Scale'!E$10)+(IF(N65="yes",1,0)*'Grading Scale'!E$11)+(IF(O65="yes",1,0)*'Grading Scale'!E$12)+(IF(P65="yes",1,0)*'Grading Scale'!E$13))/'Grading Scale'!E$14*100,0), "") -> 50 | T65: =IF(ISNUMBER(S65),VLOOKUP(S65,'Grading Scale'!$A$2:$B$14, 2), "") -> F
A66: 42759 | B66: Delaware | C66: Checkbook | D66: =IF(NOT(ISBLANK(C66)), VLOOKUP(C66,'Dataset Descriptions'!$A$2:$B$10, 2, FALSE), "") -> Transaction-level, per-agency spending records. | E66: yes | F66: yes | G66: yes | H66: yes | I66: yes | J66: yes | K66: yes | L66: yes | M66: yes | N66: yes | O66: yes | P66: no | Q66: http://checkbook.delaware.gov/expSearch.aspx | R66: Lacks a description of the purpose of the expense. | S66: =IF(NOT(ISBLANK(E66)), ROUND(((IF(E66="yes",1,0)*'Grading Scale'!E$2)+(IF(F66="yes",1,0)*'Grading Scale'!E$3)+(IF(G66="yes",1,0)*'Grading Scale'!E$4)+(IF(H66="yes",1,0)*'Grading Scale'!E$5)+(IF(I66="yes",1,0)*'Grading Scale'!E$6)+(IF(J66="yes",1,0)*'Grading Scale'!E$7)+(IF(K66="yes",1,0)*'Grading Scale'!E$8)+(IF(L66="yes",1,0)*'Grading Scale'!E$9)+(IF(M66="yes",1,0)*'Grading Scale'!E$10)+(IF(N66="yes",1,0)*'Grading Scale'!E$11)+(IF(O66="yes",1,0)*'Grading Scale'!E$12)+(IF(P66="yes",1,0)*'Grading Scale'!E$13))/'Grading Scale'!E$14*100,0), "") -> 95 | T66: =IF(ISNUMBER(S66),VLOOKUP(S66,'Grading Scale'!$A$2:$B$14, 2), "") -> A
A67: 42405 | B67: Delaware | C67: Companies | D67: =IF(NOT(ISBLANK(C67)), VLOOKUP(C67,'Dataset Descriptions'!$A$2:$B$10, 2, FALSE), "") -> The register of all corporations that exist in the state. | E67: yes | F67: yes | G67: yes | H67: no | I67: yes | J67: no | K67: no | L67: yes | M67: yes | N67: yes | O67: yes | P67: yes | Q67: https://icis.corp.delaware.gov/Ecorp/EntitySearch/NameSearch.aspx | R67: Data is incomplete unless purchased, at $20 per record. | S67: =IF(NOT(ISBLANK(E67)), ROUND(((IF(E67="yes",1,0)*'Grading Scale'!E$2)+(IF(F67="yes",1,0)*'Grading Scale'!E$3)+(IF(G67="yes",1,0)*'Grading Scale'!E$4)+(IF(H67="yes",1,0)*'Grading Scale'!E$5)+(IF(I67="yes",1,0)*'Grading Scale'!E$6)+(IF(J67="yes",1,0)*'Grading Scale'!E$7)+(IF(K67="yes",1,0)*'Grading Scale'!E$8)+(IF(L67="yes",1,0)*'Grading Scale'!E$9)+(IF(M67="yes",1,0)*'Grading Scale'!E$10)+(IF(N67="yes",1,0)*'Grading Scale'!E$11)+(IF(O67="yes",1,0)*'Grading Scale'!E$12)+(IF(P67="yes",1,0)*'Grading Scale'!E$13))/'Grading Scale'!E$14*100,0), "") -> 40 | T67: =IF(ISNUMBER(S67),VLOOKUP(S67,'Grading Scale'!$A$2:$B$14, 2), "") -> F
A68: 42405 | B68: Delaware | C68: Incarceration | D68: =IF(NOT(ISBLANK(C68)), VLOOKUP(C68,'Dataset Descriptions'!$A$2:$B$10, 2, FALSE), "") -> Per-facility inmate population records. | E68: unsure | F68: unsure | G68: unsure | H68: unsure | I68: no | J68: unsure | K68: unsure | L68: unsure | M68: unsure | N68: no | O68: unsure | P68: unsure | S68: =IF(NOT(ISBLANK(E68)), ROUND(((IF(E68="yes",1,0)*'Grading Scale'!E$2)+(IF(F68="yes",1,0)*'Grading Scale'!E$3)+(IF(G68="yes",1,0)*'Grading Scale'!E$4)+(IF(H68="yes",1,0)*'Grading Scale'!E$5)+(IF(I68="yes",1,0)*'Grading Scale'!E$6)+(IF(J68="yes",1,0)*'Grading Scale'!E$7)+(IF(K68="yes",1,0)*'Grading Scale'!E$8)+(IF(L68="yes",1,0)*'Grading Scale'!E$9)+(IF(M68="yes",1,0)*'Grading Scale'!E$10)+(IF(N68="yes",1,0)*'Grading Scale'!E$11)+(IF(O68="yes",1,0)*'Grading Scale'!E$12)+(IF(P68="yes",1,0)*'Grading Scale'!E$13))/'Grading Scale'!E$14*100,0), "") -> 0 | T68: =IF(ISNUMBER(S68),VLOOKUP(S68,'Grading Scale'!$A$2:$B$14, 2), "") -> F
A69: 42405 | B69: Delaware | C69: Legislation | D69: =IF(NOT(ISBLANK(C69)), VLOOKUP(C69,'Dataset Descriptions'!$A$2:$B$10, 2, FALSE), "") -> Bills before the legislature, and the legislators that comprise it. | E69: yes | F69: yes | G69: yes | H69: yes | I69: yes | J69: no | K69: no | L69: yes | M69: yes | N69: no | O69: no | P69: yes | Q69: http://legis.delaware.gov/ | S69: =IF(NOT(ISBLANK(E69)), ROUND(((IF(E69="yes",1,0)*'Grading Scale'!E$2)+(IF(F69="yes",1,0)*'Grading Scale'!E$3)+(IF(G69="yes",1,0)*'Grading Scale'!E$4)+(IF(H69="yes",1,0)*'Grading Scale'!E$5)+(IF(I69="yes",1,0)*'Grading Scale'!E$6)+(IF(J69="yes",1,0)*'Grading Scale'!E$7)+(IF(K69="yes",1,0)*'Grading Scale'!E$8)+(IF(L69="yes",1,0)*'Grading Scale'!E$9)+(IF(M69="yes",1,0)*'Grading Scale'!E$10)+(IF(N69="yes",1,0)*'Grading Scale'!E$11)+(IF(O69="yes",1,0)*'Grading Scale'!E$12)+(IF(P69="yes",1,0)*'Grading Scale'!E$13))/'Grading Scale'!E$14*100,0), "") -> 45 | T69: =IF(ISNUMBER(S69),VLOOKUP(S69,'Grading Scale'!$A$2:$B$14, 2), "") -> F
A70: 42405 | B70: Delaware | C70: Population Projections | D70: =IF(NOT(ISBLANK(C70)), VLOOKUP(C70,'Dataset Descriptions'!$A$2:$B$10, 2, FALSE), "") -> Forecasts of municipal-level changes in population over coming years. | E70: yes | F70: yes | G70: yes | H70: yes | I70: yes | J70: no | K70: yes | L70: yes | M70: yes | N70: yes | O70: no | P70: no | Q70: http://stateplanning.delaware.gov/information/dpc_projections.shtml | R70: Data is provided as an Excel file, but it's formatted to be parsed by humans, not software, so it cannot be graded as machine-readable. Localities lack GNIS IDs or FIPS code, so data is incomplete. | S70: =IF(NOT(ISBLANK(E70)), ROUND(((IF(E70="yes",1,0)*'Grading Scale'!E$2)+(IF(F70="yes",1,0)*'Grading Scale'!E$3)+(IF(G70="yes",1,0)*'Grading Scale'!E$4)+(IF(H70="yes",1,0)*'Grading Scale'!E$5)+(IF(I70="yes",1,0)*'Grading Scale'!E$6)+(IF(J70="yes",1,0)*'Grading Scale'!E$7)+(IF(K70="yes",1,0)*'Grading Scale'!E$8)+(IF(L70="yes",1,0)*'Grading Scale'!E$9)+(IF(M70="yes",1,0)*'Grading Scale'!E$10)+(IF(N70="yes",1,0)*'Grading Scale'!E$11)+(IF(O70="yes",1,0)*'Grading Scale'!E$12)+(IF(P70="yes",1,0)*'Grading Scale'!E$13))/'Grading Scale'!E$14*100,0), "") -> 50 | T70: =IF(ISNUMBER(S70),VLOOKUP(S70,'Grading Scale'!$A$2:$B$14, 2), "") -> F
A71: 42405 | B71: Delaware | C71: Real Estate | D71: =IF(NOT(ISBLANK(C71)), VLOOKUP(C71,'Dataset Descriptions'!$A$2:$B$10, 2, FALSE), "") -> State-owned land and buildings. | E71: unsure | F71: unsure | G71: unsure | H71: unsure | I71: no | J71: unsure | K71: unsure | L71: unsure | M71: unsure | N71: no | O71: unsure | P71: unsure | S71: =IF(NOT(ISBLANK(E71)), ROUND(((IF(E71="yes",1,0)*'Grading Scale'!E$2)+(IF(F71="yes",1,0)*'Grading Scale'!E$3)+(IF(G71="yes",1,0)*'Grading Scale'!E$4)+(IF(H71="yes",1,0)*'Grading Scale'!E$5)+(IF(I71="yes",1,0)*'Grading Scale'!E$6)+(IF(J71="yes",1,0)*'Grading Scale'!E$7)+(IF(K71="yes",1,0)*'Grading Scale'!E$8)+(IF(L71="yes",1,0)*'Grading Scale'!E$9)+(IF(M71="yes",1,0)*'Grading Scale'!E$10)+(IF(N71="yes",1,0)*'Grading Scale'!E$11)+(IF(O71="yes",1,0)*'Grading Scale'!E$12)+(IF(P71="yes",1,0)*'Grading Scale'!E$13))/'Grading Scale'!E$14*100,0), "") -> 0 | T71: =IF(ISNUMBER(S71),VLOOKUP(S71,'Grading Scale'!$A$2:$B$14, 2), "") -> F
A72: 42759 | B72: Delaware | C72: Restaurant Inspections | D72: =IF(NOT(ISBLANK(C72)), VLOOKUP(C72,'Dataset Descriptions'!$A$2:$B$10, 2, FALSE), "") -> Health inspections of establishments that serve food to the public. | E72: yes | F72: yes | G72: yes | H72: yes | I72: yes | J72: yes | K72: yes | L72: yes | M72: yes | N72: yes | O72: yes | P72: no | Q72: http://www.dhss.delaware.gov/dhss/dph/hsp/ | R72: No IDs are provided. | S72: =IF(NOT(ISBLANK(E72)), ROUND(((IF(E72="yes",1,0)*'Grading Scale'!E$2)+(IF(F72="yes",1,0)*'Grading Scale'!E$3)+(IF(G72="yes",1,0)*'Grading Scale'!E$4)+(IF(H72="yes",1,0)*'Grading Scale'!E$5)+(IF(I72="yes",1,0)*'Grading Scale'!E$6)+(IF(J72="yes",1,0)*'Grading Scale'!E$7)+(IF(K72="yes",1,0)*'Grading Scale'!E$8)+(IF(L72="yes",1,0)*'Grading Scale'!E$9)+(IF(M72="yes",1,0)*'Grading Scale'!E$10)+(IF(N72="yes",1,0)*'Grading Scale'!E$11)+(IF(O72="yes",1,0)*'Grading Scale'!E$12)+(IF(P72="yes",1,0)*'Grading Scale'!E$13))/'Grading Scale'!E$14*100,0), "") -> 95 | T72: =IF(ISNUMBER(S72),VLOOKUP(S72,'Grading Scale'!$A$2:$B$14, 2), "") -> A
A73: 42405 | B73: Delaware | C73: Vehicle Crashes | D73: =IF(NOT(ISBLANK(C73)), VLOOKUP(C73,'Dataset Descriptions'!$A$2:$B$10, 2, FALSE), "") -> Incident-level reportable motor vehicle crash records. | E73: yes | F73: yes | G73: unsure | H73: unsure | I73: no | J73: yes | K73: unsure | L73: unsure | M73: yes | N73: no | O73: unsure | P73: yes | R73: Delaware adheres to the Model Minimum Uniform Crash Criteria, so their data can be known to be complete, timely, etc. But they offer none of this data online. | S73: =IF(NOT(ISBLANK(E73)), ROUND(((IF(E73="yes",1,0)*'Grading Scale'!E$2)+(IF(F73="yes",1,0)*'Grading Scale'!E$3)+(IF(G73="yes",1,0)*'Grading Scale'!E$4)+(IF(H73="yes",1,0)*'Grading Scale'!E$5)+(IF(I73="yes",1,0)*'Grading Scale'!E$6)+(IF(J73="yes",1,0)*'Grading Scale'!E$7)+(IF(K73="yes",1,0)*'Grading Scale'!E$8)+(IF(L73="yes",1,0)*'Grading Scale'!E$9)+(IF(M73="yes",1,0)*'Grading Scale'!E$10)+(IF(N73="yes",1,0)*'Grading Scale'!E$11)+(IF(O73="yes",1,0)*'Grading Scale'!E$12)+(IF(P73="yes",1,0)*'Grading Scale'!E$13))/'Grading Scale'!E$14*100,0), "") -> 55 | T73: =IF(ISNUMBER(S73),VLOOKUP(S73,'Grading Scale'!$A$2:$B$14, 2), "") -> F
A74: 42434 | B74: Florida | C74: Address Points | D74: =IF(NOT(ISBLANK(C74)), VLOOKUP(C74,'Dataset Descriptions'!$A$2:$B$10, 2, FALSE), "") -> The geographic coordinates for physical addresses. | E74: no | F74: no | G74: no | H74: no | I74: no | J74: no | K74: no | L74: no | M74: no | N74: no | O74: no | P74: no | S74: =IF(NOT(ISBLANK(E74)), ROUND(((IF(E74="yes",1,0)*'Grading Scale'!E$2)+(IF(F74="yes",1,0)*'Grading Scale'!E$3)+(IF(G74="yes",1,0)*'Grading Scale'!E$4)+(IF(H74="yes",1,0)*'Grading Scale'!E$5)+(IF(I74="yes",1,0)*'Grading Scale'!E$6)+(IF(J74="yes",1,0)*'Grading Scale'!E$7)+(IF(K74="yes",1,0)*'Grading Scale'!E$8)+(IF(L74="yes",1,0)*'Grading Scale'!E$9)+(IF(M74="yes",1,0)*'Grading Scale'!E$10)+(IF(N74="yes",1,0)*'Grading Scale'!E$11)+(IF(O74="yes",1,0)*'Grading Scale'!E$12)+(IF(P74="yes",1,0)*'Grading Scale'!E$13))/'Grading Scale'!E$14*100,0), "") -> 0 | T74: =IF(ISNUMBER(S74),VLOOKUP(S74,'Grading Scale'!$A$2:$B$14, 2), "") -> F
A75: 42360 | B75: Florida | C75: Checkbook | D75: =IF(NOT(ISBLANK(C75)), VLOOKUP(C75,'Dataset Descriptions'!$A$2:$B$10, 2, FALSE), "") -> Transaction-level, per-agency spending records. | E75: yes | F75: yes | G75: yes | H75: yes | I75: yes | J75: yes | K75: yes | L75: no | M75: yes | N75: no | O75: no | P75: no | Q75: http://www.myfloridacfo.com/transparency/vendorpayments.aspx | R75: Provided as pipe-delimited text with no column headers, one file per year. Lacks a specific description of the purpose of the expenditure, and instead just provides a general category. | S75: =IF(NOT(ISBLANK(E75)), ROUND(((IF(E75="yes",1,0)*'Grading Scale'!E$2)+(IF(F75="yes",1,0)*'Grading Scale'!E$3)+(IF(G75="yes",1,0)*'Grading Scale'!E$4)+(IF(H75="yes",1,0)*'Grading Scale'!E$5)+(IF(I75="yes",1,0)*'Grading Scale'!E$6)+(IF(J75="yes",1,0)*'Grading Scale'!E$7)+(IF(K75="yes",1,0)*'Grading Scale'!E$8)+(IF(L75="yes",1,0)*'Grading Scale'!E$9)+(IF(M75="yes",1,0)*'Grading Scale'!E$10)+(IF(N75="yes",1,0)*'Grading Scale'!E$11)+(IF(O75="yes",1,0)*'Grading Scale'!E$12)+(IF(P75="yes",1,0)*'Grading Scale'!E$13))/'Grading Scale'!E$14*100,0), "") -> 80 | T75: =IF(ISNUMBER(S75),VLOOKUP(S75,'Grading Scale'!$A$2:$B$14, 2), "") -> B−
A76: 42396 | B76: Florida | C76: Companies | D76: =IF(NOT(ISBLANK(C76)), VLOOKUP(C76,'Dataset Descriptions'!$A$2:$B$10, 2, FALSE), "") -> The register of all corporations that exist in the state. | E76: yes | F76: yes | G76: yes | H76: yes | I76: yes | J76: yes | K76: yes | L76: no | M76: yes | N76: no | O76: no | P76: yes | Q76: http://sunbiz.org/cor_downld.html | R76: Data is provided as fixed-width ASCII files, with a new files created each day as a rolling changelog. Quarterly updates are also available. | S76: =IF(NOT(ISBLANK(E76)), ROUND(((IF(E76="yes",1,0)*'Grading Scale'!E$2)+(IF(F76="yes",1,0)*'Grading Scale'!E$3)+(IF(G76="yes",1,0)*'Grading Scale'!E$4)+(IF(H76="yes",1,0)*'Grading Scale'!E$5)+(IF(I76="yes",1,0)*'Grading Scale'!E$6)+(IF(J76="yes",1,0)*'Grading Scale'!E$7)+(IF(K76="yes",1,0)*'Grading Scale'!E$8)+(IF(L76="yes",1,0)*'Grading Scale'!E$9)+(IF(M76="yes",1,0)*'Grading Scale'!E$10)+(IF(N76="yes",1,0)*'Grading Scale'!E$11)+(IF(O76="yes",1,0)*'Grading Scale'!E$12)+(IF(P76="yes",1,0)*'Grading Scale'!E$13))/'Grading Scale'!E$14*100,0), "") -> 85 | T76: =IF(ISNUMBER(S76),VLOOKUP(S76,'Grading Scale'!$A$2:$B$14, 2), "") -> B
A77: 42396 | B77: Florida | C77: Incarceration | D77: =IF(NOT(ISBLANK(C77)), VLOOKUP(C77,'Dataset Descriptions'!$A$2:$B$10, 2, FALSE), "") -> Per-facility inmate population records. | E77: yes | F77: yes | G77: yes | H77: yes | I77: yes | J77: no | K77: no | L77: yes | M77: yes | N77: no | O77: no | P77: no | Q77: http://www.dc.state.fl.us/pub/pop/facility/index.html | R77: Only aviailable as HTML, and lacks data about facilities' capacities or historical data from more than 6 months ago. | S77: =IF(NOT(ISBLANK(E77)), ROUND(((IF(E77="yes",1,0)*'Grading Scale'!E$2)+(IF(F77="yes",1,0)*'Grading Scale'!E$3)+(IF(G77="yes",1,0)*'Grading Scale'!E$4)+(IF(H77="yes",1,0)*'Grading Scale'!E$5)+(IF(I77="yes",1,0)*'Grading Scale'!E$6)+(IF(J77="yes",1,0)*'Grading Scale'!E$7)+(IF(K77="yes",1,0)*'Grading Scale'!E$8)+(IF(L77="yes",1,0)*'Grading Scale'!E$9)+(IF(M77="yes",1,0)*'Grading Scale'!E$10)+(IF(N77="yes",1,0)*'Grading Scale'!E$11)+(IF(O77="yes",1,0)*'Grading Scale'!E$12)+(IF(P77="yes",1,0)*'Grading Scale'!E$13))/'Grading Scale'!E$14*100,0), "") -> 40 | T77: =IF(ISNUMBER(S77),VLOOKUP(S77,'Grading Scale'!$A$2:$B$14, 2), "") -> F
A78: 42360 | B78: Florida | C78: Legislation | D78: =IF(NOT(ISBLANK(C78)), VLOOKUP(C78,'Dataset Descriptions'!$A$2:$B$10, 2, FALSE), "") -> Bills before the legislature, and the legislators that comprise it. | E78: yes | F78: yes | G78: yes | H78: yes | I78: yes | J78: no | K78: no | L78: no | M78: yes | N78: no | O78: no | P78: yes | Q78: http://www.leg.state.fl.us/ | S78: =IF(NOT(ISBLANK(E78)), ROUND(((IF(E78="yes",1,0)*'Grading Scale'!E$2)+(IF(F78="yes",1,0)*'Grading Scale'!E$3)+(IF(G78="yes",1,0)*'Grading Scale'!E$4)+(IF(H78="yes",1,0)*'Grading Scale'!E$5)+(IF(I78="yes",1,0)*'Grading Scale'!E$6)+(IF(J78="yes",1,0)*'Grading Scale'!E$7)+(IF(K78="yes",1,0)*'Grading Scale'!E$8)+(IF(L78="yes",1,0)*'Grading Scale'!E$9)+(IF(M78="yes",1,0)*'Grading Scale'!E$10)+(IF(N78="yes",1,0)*'Grading Scale'!E$11)+(IF(O78="yes",1,0)*'Grading Scale'!E$12)+(IF(P78="yes",1,0)*'Grading Scale'!E$13))/'Grading Scale'!E$14*100,0), "") -> 40 | T78: =IF(ISNUMBER(S78),VLOOKUP(S78,'Grading Scale'!$A$2:$B$14, 2), "") -> F
A79: 42338 | B79: Florida | C79: Population Projections | D79: =IF(NOT(ISBLANK(C79)), VLOOKUP(C79,'Dataset Descriptions'!$A$2:$B$10, 2, FALSE), "") -> Forecasts of municipal-level changes in population over coming years. | E79: yes | F79: yes | G79: yes | H79: yes | I79: yes | J79: no | K79: no | L79: no | M79: yes | N79: no | O79: no | P79: no | Q79: http://edr.state.fl.us/Content/population-demographics/data/ | S79: =IF(NOT(ISBLANK(E79)), ROUND(((IF(E79="yes",1,0)*'Grading Scale'!E$2)+(IF(F79="yes",1,0)*'Grading Scale'!E$3)+(IF(G79="yes",1,0)*'Grading Scale'!E$4)+(IF(H79="yes",1,0)*'Grading Scale'!E$5)+(IF(I79="yes",1,0)*'Grading Scale'!E$6)+(IF(J79="yes",1,0)*'Grading Scale'!E$7)+(IF(K79="yes",1,0)*'Grading Scale'!E$8)+(IF(L79="yes",1,0)*'Grading Scale'!E$9)+(IF(M79="yes",1,0)*'Grading Scale'!E$10)+(IF(N79="yes",1,0)*'Grading Scale'!E$11)+(IF(O79="yes",1,0)*'Grading Scale'!E$12)+(IF(P79="yes",1,0)*'Grading Scale'!E$13))/'Grading Scale'!E$14*100,0), "") -> 35 | T79: =IF(ISNUMBER(S79),VLOOKUP(S79,'Grading Scale'!$A$2:$B$14, 2), "") -> F
A80: 42338 | B80: Florida | C80: Real Estate | D80: =IF(NOT(ISBLANK(C80)), VLOOKUP(C80,'Dataset Descriptions'!$A$2:$B$10, 2, FALSE), "") -> State-owned land and buildings. | E80: yes | F80: yes | G80: yes | H80: yes | I80: yes | J80: no | K80: no | L80: no | M80: no | N80: no | O80: no | P80: yes | Q80: http://www.dms.myflorida.com/business_operations/real_estate_development_and_management/facilities_management/florida_state_owned_lands_and_records_information_system_fl_solaris | R80: Only PDFs are provided. Data is from 2013, while other data on the site is updated constantly. | S80: =IF(NOT(ISBLANK(E80)), ROUND(((IF(E80="yes",1,0)*'Grading Scale'!E$2)+(IF(F80="yes",1,0)*'Grading Scale'!E$3)+(IF(G80="yes",1,0)*'Grading Scale'!E$4)+(IF(H80="yes",1,0)*'Grading Scale'!E$5)+(IF(I80="yes",1,0)*'Grading Scale'!E$6)+(IF(J80="yes",1,0)*'Grading Scale'!E$7)+(IF(K80="yes",1,0)*'Grading Scale'!E$8)+(IF(L80="yes",1,0)*'Grading Scale'!E$9)+(IF(M80="yes",1,0)*'Grading Scale'!E$10)+(IF(N80="yes",1,0)*'Grading Scale'!E$11)+(IF(O80="yes",1,0)*'Grading Scale'!E$12)+(IF(P80="yes",1,0)*'Grading Scale'!E$13))/'Grading Scale'!E$14*100,0), "") -> 35 | T80: =IF(ISNUMBER(S80),VLOOKUP(S80,'Grading Scale'!$A$2:$B$14, 2), "") -> F
A81: 42338 | B81: Florida | C81: Restaurant Inspections | D81: =IF(NOT(ISBLANK(C81)), VLOOKUP(C81,'Dataset Descriptions'!$A$2:$B$10, 2, FALSE), "") -> Health inspections of establishments that serve food to the public. | E81: yes | F81: yes | G81: yes | H81: yes | I81: yes | J81: no | K81: no | L81: no | M81: yes | N81: no | O81: no | P81: yes | Q81: http://www.floridahealth.gov///statistics-and-data/eh-tracking-and-reporting/food-hygiene.html | S81: =IF(NOT(ISBLANK(E81)), ROUND(((IF(E81="yes",1,0)*'Grading Scale'!E$2)+(IF(F81="yes",1,0)*'Grading Scale'!E$3)+(IF(G81="yes",1,0)*'Grading Scale'!E$4)+(IF(H81="yes",1,0)*'Grading Scale'!E$5)+(IF(I81="yes",1,0)*'Grading Scale'!E$6)+(IF(J81="yes",1,0)*'Grading Scale'!E$7)+(IF(K81="yes",1,0)*'Grading Scale'!E$8)+(IF(L81="yes",1,0)*'Grading Scale'!E$9)+(IF(M81="yes",1,0)*'Grading Scale'!E$10)+(IF(N81="yes",1,0)*'Grading Scale'!E$11)+(IF(O81="yes",1,0)*'Grading Scale'!E$12)+(IF(P81="yes",1,0)*'Grading Scale'!E$13))/'Grading Scale'!E$14*100,0), "") -> 40 | T81: =IF(ISNUMBER(S81),VLOOKUP(S81,'Grading Scale'!$A$2:$B$14, 2), "") -> F
A82: 42338 | B82: Florida | C82: Vehicle Crashes | D82: =IF(NOT(ISBLANK(C82)), VLOOKUP(C82,'Dataset Descriptions'!$A$2:$B$10, 2, FALSE), "") -> Incident-level reportable motor vehicle crash records. | E82: yes | F82: yes | G82: yes | H82: yes | I82: yes | J82: no | K82: no | L82: no | M82: no | N82: no | O82: no | P82: no | Q82: http://www.flhsmv.gov/resource-center/crash-citation-reports/ | R82: Copyright statement in footer says the data is owned by “Appriss, Inc.” | S82: =IF(NOT(ISBLANK(E82)), ROUND(((IF(E82="yes",1,0)*'Grading Scale'!E$2)+(IF(F82="yes",1,0)*'Grading Scale'!E$3)+(IF(G82="yes",1,0)*'Grading Scale'!E$4)+(IF(H82="yes",1,0)*'Grading Scale'!E$5)+(IF(I82="yes",1,0)*'Grading Scale'!E$6)+(IF(J82="yes",1,0)*'Grading Scale'!E$7)+(IF(K82="yes",1,0)*'Grading Scale'!E$8)+(IF(L82="yes",1,0)*'Grading Scale'!E$9)+(IF(M82="yes",1,0)*'Grading Scale'!E$10)+(IF(N82="yes",1,0)*'Grading Scale'!E$11)+(IF(O82="yes",1,0)*'Grading Scale'!E$12)+(IF(P82="yes",1,0)*'Grading Scale'!E$13))/'Grading Scale'!E$14*100,0), "") -> 30 | T82: =IF(ISNUMBER(S82),VLOOKUP(S82,'Grading Scale'!$A$2:$B$14, 2), "") -> F
A83: 42338 | B83: Georgia | C83: Address Points | D83: =IF(NOT(ISBLANK(C83)), VLOOKUP(C83,'Dataset Descriptions'!$A$2:$B$10, 2, FALSE), "") -> The geographic coordinates for physical addresses. | E83: no | F83: no | G83: no | H83: no | I83: no | J83: no | K83: no | L83: no | M83: no | N83: no | O83: no | P83: no | S83: =IF(NOT(ISBLANK(E83)), ROUND(((IF(E83="yes",1,0)*'Grading Scale'!E$2)+(IF(F83="yes",1,0)*'Grading Scale'!E$3)+(IF(G83="yes",1,0)*'Grading Scale'!E$4)+(IF(H83="yes",1,0)*'Grading Scale'!E$5)+(IF(I83="yes",1,0)*'Grading Scale'!E$6)+(IF(J83="yes",1,0)*'Grading Scale'!E$7)+(IF(K83="yes",1,0)*'Grading Scale'!E$8)+(IF(L83="yes",1,0)*'Grading Scale'!E$9)+(IF(M83="yes",1,0)*'Grading Scale'!E$10)+(IF(N83="yes",1,0)*'Grading Scale'!E$11)+(IF(O83="yes",1,0)*'Grading Scale'!E$12)+(IF(P83="yes",1,0)*'Grading Scale'!E$13))/'Grading Scale'!E$14*100,0), "") -> 0 | T83: =IF(ISNUMBER(S83),VLOOKUP(S83,'Grading Scale'!$A$2:$B$14, 2), "") -> F
A84: 42338 | B84: Georgia | C84: Checkbook | D84: =IF(NOT(ISBLANK(C84)), VLOOKUP(C84,'Dataset Descriptions'!$A$2:$B$10, 2, FALSE), "") -> Transaction-level, per-agency spending records. | E84: yes | F84: yes | G84: yes | H84: yes | I84: yes | J84: yes | K84: no | L84: no | M84: no | N84: no | O84: no | P84: no | Q84: http://www.open.georgia.gov/psa/poSearch.aud | R84: Query results can be exported as CSV. Footer says data is copyright “DOAA.” Transactions have no date, so it’s impossible to know how current that the data is. Data also lacks check number and expense category. | S84: =IF(NOT(ISBLANK(E84)), ROUND(((IF(E84="yes",1,0)*'Grading Scale'!E$2)+(IF(F84="yes",1,0)*'Grading Scale'!E$3)+(IF(G84="yes",1,0)*'Grading Scale'!E$4)+(IF(H84="yes",1,0)*'Grading Scale'!E$5)+(IF(I84="yes",1,0)*'Grading Scale'!E$6)+(IF(J84="yes",1,0)*'Grading Scale'!E$7)+(IF(K84="yes",1,0)*'Grading Scale'!E$8)+(IF(L84="yes",1,0)*'Grading Scale'!E$9)+(IF(M84="yes",1,0)*'Grading Scale'!E$10)+(IF(N84="yes",1,0)*'Grading Scale'!E$11)+(IF(O84="yes",1,0)*'Grading Scale'!E$12)+(IF(P84="yes",1,0)*'Grading Scale'!E$13))/'Grading Scale'!E$14*100,0), "") -> 70 | T84: =IF(ISNUMBER(S84),VLOOKUP(S84,'Grading Scale'!$A$2:$B$14, 2), "") -> C−
A85: 42338 | B85: Georgia | C85: Companies | D85: =IF(NOT(ISBLANK(C85)), VLOOKUP(C85,'Dataset Descriptions'!$A$2:$B$10, 2, FALSE), "") -> The register of all corporations that exist in the state. | E85: yes | F85: yes | G85: yes | H85: no | I85: yes | J85: yes | K85: yes | L85: yes | M85: yes | N85: no | O85: yes | P85: yes | Q85: http://gta.georgia.gov/bulk-corporations-data | R85: Viewing information in HTML is free, but the data is sold for $1,000. Purchased data is provided as pipe-delimited text. Site uses HTTPS. | S85: =IF(NOT(ISBLANK(E85)), ROUND(((IF(E85="yes",1,0)*'Grading Scale'!E$2)+(IF(F85="yes",1,0)*'Grading Scale'!E$3)+(IF(G85="yes",1,0)*'Grading Scale'!E$4)+(IF(H85="yes",1,0)*'Grading Scale'!E$5)+(IF(I85="yes",1,0)*'Grading Scale'!E$6)+(IF(J85="yes",1,0)*'Grading Scale'!E$7)+(IF(K85="yes",1,0)*'Grading Scale'!E$8)+(IF(L85="yes",1,0)*'Grading Scale'!E$9)+(IF(M85="yes",1,0)*'Grading Scale'!E$10)+(IF(N85="yes",1,0)*'Grading Scale'!E$11)+(IF(O85="yes",1,0)*'Grading Scale'!E$12)+(IF(P85="yes",1,0)*'Grading Scale'!E$13))/'Grading Scale'!E$14*100,0), "") -> 80 | T85: =IF(ISNUMBER(S85),VLOOKUP(S85,'Grading Scale'!$A$2:$B$14, 2), "") -> B−
A86: 42338 | B86: Georgia | C86: Incarceration | D86: =IF(NOT(ISBLANK(C86)), VLOOKUP(C86,'Dataset Descriptions'!$A$2:$B$10, 2, FALSE), "") -> Per-facility inmate population records. | E86: no | F86: no | G86: no | H86: no | I86: no | J86: no | K86: no | L86: no | M86: no | N86: no | S86: =IF(NOT(ISBLANK(E86)), ROUND(((IF(E86="yes",1,0)*'Grading Scale'!E$2)+(IF(F86="yes",1,0)*'Grading Scale'!E$3)+(IF(G86="yes",1,0)*'Grading Scale'!E$4)+(IF(H86="yes",1,0)*'Grading Scale'!E$5)+(IF(I86="yes",1,0)*'Grading Scale'!E$6)+(IF(J86="yes",1,0)*'Grading Scale'!E$7)+(IF(K86="yes",1,0)*'Grading Scale'!E$8)+(IF(L86="yes",1,0)*'Grading Scale'!E$9)+(IF(M86="yes",1,0)*'Grading Scale'!E$10)+(IF(N86="yes",1,0)*'Grading Scale'!E$11)+(IF(O86="yes",1,0)*'Grading Scale'!E$12)+(IF(P86="yes",1,0)*'Grading Scale'!E$13))/'Grading Scale'!E$14*100,0), "") -> 0 | T86: =IF(ISNUMBER(S86),VLOOKUP(S86,'Grading Scale'!$A$2:$B$14, 2), "") -> F
A87: 42338 | B87: Georgia | C87: Legislation | D87: =IF(NOT(ISBLANK(C87)), VLOOKUP(C87,'Dataset Descriptions'!$A$2:$B$10, 2, FALSE), "") -> Bills before the legislature, and the legislators that comprise it. | E87: yes | F87: yes | G87: yes | H87: yes | I87: yes | J87: no | K87: no | L87: yes | M87: yes | N87: no | O87: no | P87: yes | Q87: http://www.legis.ga.gov/ | S87: =IF(NOT(ISBLANK(E87)), ROUND(((IF(E87="yes",1,0)*'Grading Scale'!E$2)+(IF(F87="yes",1,0)*'Grading Scale'!E$3)+(IF(G87="yes",1,0)*'Grading Scale'!E$4)+(IF(H87="yes",1,0)*'Grading Scale'!E$5)+(IF(I87="yes",1,0)*'Grading Scale'!E$6)+(IF(J87="yes",1,0)*'Grading Scale'!E$7)+(IF(K87="yes",1,0)*'Grading Scale'!E$8)+(IF(L87="yes",1,0)*'Grading Scale'!E$9)+(IF(M87="yes",1,0)*'Grading Scale'!E$10)+(IF(N87="yes",1,0)*'Grading Scale'!E$11)+(IF(O87="yes",1,0)*'Grading Scale'!E$12)+(IF(P87="yes",1,0)*'Grading Scale'!E$13))/'Grading Scale'!E$14*100,0), "") -> 45 | T87: =IF(ISNUMBER(S87),VLOOKUP(S87,'Grading Scale'!$A$2:$B$14, 2), "") -> F
A88: 42354 | B88: Georgia | C88: Population Projections | D88: =IF(NOT(ISBLANK(C88)), VLOOKUP(C88,'Dataset Descriptions'!$A$2:$B$10, 2, FALSE), "") -> Forecasts of municipal-level changes in population over coming years. | E88: yes | F88: yes | G88: yes | H88: yes | I88: no | J88: unsure | K88: no | L88: yes | M88: yes | N88: no | O88: no | Q88: https://opb.georgia.gov/population-projections | R88: Data is obtained by e-mailing a PDF request form. That has not yet been attempted. Although the site uses HTTPS, that's moot, since the data is sent via email. | S88: =IF(NOT(ISBLANK(E88)), ROUND(((IF(E88="yes",1,0)*'Grading Scale'!E$2)+(IF(F88="yes",1,0)*'Grading Scale'!E$3)+(IF(G88="yes",1,0)*'Grading Scale'!E$4)+(IF(H88="yes",1,0)*'Grading Scale'!E$5)+(IF(I88="yes",1,0)*'Grading Scale'!E$6)+(IF(J88="yes",1,0)*'Grading Scale'!E$7)+(IF(K88="yes",1,0)*'Grading Scale'!E$8)+(IF(L88="yes",1,0)*'Grading Scale'!E$9)+(IF(M88="yes",1,0)*'Grading Scale'!E$10)+(IF(N88="yes",1,0)*'Grading Scale'!E$11)+(IF(O88="yes",1,0)*'Grading Scale'!E$12)+(IF(P88="yes",1,0)*'Grading Scale'!E$13))/'Grading Scale'!E$14*100,0), "") -> 35 | T88: =IF(ISNUMBER(S88),VLOOKUP(S88,'Grading Scale'!$A$2:$B$14, 2), "") -> F
A89: 42338 | B89: Georgia | C89: Real Estate | D89: =IF(NOT(ISBLANK(C89)), VLOOKUP(C89,'Dataset Descriptions'!$A$2:$B$10, 2, FALSE), "") -> State-owned land and buildings. | E89: yes | F89: yes | G89: yes | H89: yes | I89: yes | J89: no | K89: no | L89: yes | M89: yes | N89: no | O89: yes | P89: no | Q89: http://gspc.georgia.gov/ | R89: Properties don't have any consistent location identifiers. Site uses HTTPS. | S89: =IF(NOT(ISBLANK(E89)), ROUND(((IF(E89="yes",1,0)*'Grading Scale'!E$2)+(IF(F89="yes",1,0)*'Grading Scale'!E$3)+(IF(G89="yes",1,0)*'Grading Scale'!E$4)+(IF(H89="yes",1,0)*'Grading Scale'!E$5)+(IF(I89="yes",1,0)*'Grading Scale'!E$6)+(IF(J89="yes",1,0)*'Grading Scale'!E$7)+(IF(K89="yes",1,0)*'Grading Scale'!E$8)+(IF(L89="yes",1,0)*'Grading Scale'!E$9)+(IF(M89="yes",1,0)*'Grading Scale'!E$10)+(IF(N89="yes",1,0)*'Grading Scale'!E$11)+(IF(O89="yes",1,0)*'Grading Scale'!E$12)+(IF(P89="yes",1,0)*'Grading Scale'!E$13))/'Grading Scale'!E$14*100,0), "") -> 45 | T89: =IF(ISNUMBER(S89),VLOOKUP(S89,'Grading Scale'!$A$2:$B$14, 2), "") -> F
A90: 42338 | B90: Georgia | C90: Restaurant Inspections | D90: =IF(NOT(ISBLANK(C90)), VLOOKUP(C90,'Dataset Descriptions'!$A$2:$B$10, 2, FALSE), "") -> Health inspections of establishments that serve food to the public. | E90: yes | F90: yes | G90: yes | H90: yes | I90: yes | J90: no | K90: no | L90: yes | M90: yes | N90: no | O90: no | P90: no | Q90: https://dph.georgia.gov/environmental-health-inspections | R90: Not all counties’ data is available. | S90: =IF(NOT(ISBLANK(E90)), ROUND(((IF(E90="yes",1,0)*'Grading Scale'!E$2)+(IF(F90="yes",1,0)*'Grading Scale'!E$3)+(IF(G90="yes",1,0)*'Grading Scale'!E$4)+(IF(H90="yes",1,0)*'Grading Scale'!E$5)+(IF(I90="yes",1,0)*'Grading Scale'!E$6)+(IF(J90="yes",1,0)*'Grading Scale'!E$7)+(IF(K90="yes",1,0)*'Grading Scale'!E$8)+(IF(L90="yes",1,0)*'Grading Scale'!E$9)+(IF(M90="yes",1,0)*'Grading Scale'!E$10)+(IF(N90="yes",1,0)*'Grading Scale'!E$11)+(IF(O90="yes",1,0)*'Grading Scale'!E$12)+(IF(P90="yes",1,0)*'Grading Scale'!E$13))/'Grading Scale'!E$14*100,0), "") -> 40 | T90: =IF(ISNUMBER(S90),VLOOKUP(S90,'Grading Scale'!$A$2:$B$14, 2), "") -> F
A91: 42338 | B91: Georgia | C91: Vehicle Crashes | D91: =IF(NOT(ISBLANK(C91)), VLOOKUP(C91,'Dataset Descriptions'!$A$2:$B$10, 2, FALSE), "") -> Incident-level reportable motor vehicle crash records. | E91: yes | F91: yes | G91: yes | H91: yes | I91: yes | J91: no | K91: no | L91: no | M91: yes | N91: no | O91: no | P91: no | Q91: http://www.gahighwaysafety.org/research/ | R91: These are statistics, not data. Provided only as PDFs. | S91: =IF(NOT(ISBLANK(E91)), ROUND(((IF(E91="yes",1,0)*'Grading Scale'!E$2)+(IF(F91="yes",1,0)*'Grading Scale'!E$3)+(IF(G91="yes",1,0)*'Grading Scale'!E$4)+(IF(H91="yes",1,0)*'Grading Scale'!E$5)+(IF(I91="yes",1,0)*'Grading Scale'!E$6)+(IF(J91="yes",1,0)*'Grading Scale'!E$7)+(IF(K91="yes",1,0)*'Grading Scale'!E$8)+(IF(L91="yes",1,0)*'Grading Scale'!E$9)+(IF(M91="yes",1,0)*'Grading Scale'!E$10)+(IF(N91="yes",1,0)*'Grading Scale'!E$11)+(IF(O91="yes",1,0)*'Grading Scale'!E$12)+(IF(P91="yes",1,0)*'Grading Scale'!E$13))/'Grading Scale'!E$14*100,0), "") -> 35 | T91: =IF(ISNUMBER(S91),VLOOKUP(S91,'Grading Scale'!$A$2:$B$14, 2), "") -> F
A92: 42396 | B92: Hawaii | C92: Address Points | D92: =IF(NOT(ISBLANK(C92)), VLOOKUP(C92,'Dataset Descriptions'!$A$2:$B$10, 2, FALSE), "") -> The geographic coordinates for physical addresses. | E92: unsure | F92: unsure | G92: unsure | H92: unsure | I92: no | J92: unsure | K92: unsure | L92: unsure | M92: unsure | N92: no | O92: unsure | P92: unsure | R92: There is no evidence that Hawaii gathers or shares this information. If they did, it would likely be at (http://planning.hawaii.gov/gis/download-gis-data/). | S92: =IF(NOT(ISBLANK(E92)), ROUND(((IF(E92="yes",1,0)*'Grading Scale'!E$2)+(IF(F92="yes",1,0)*'Grading Scale'!E$3)+(IF(G92="yes",1,0)*'Grading Scale'!E$4)+(IF(H92="yes",1,0)*'Grading Scale'!E$5)+(IF(I92="yes",1,0)*'Grading Scale'!E$6)+(IF(J92="yes",1,0)*'Grading Scale'!E$7)+(IF(K92="yes",1,0)*'Grading Scale'!E$8)+(IF(L92="yes",1,0)*'Grading Scale'!E$9)+(IF(M92="yes",1,0)*'Grading Scale'!E$10)+(IF(N92="yes",1,0)*'Grading Scale'!E$11)+(IF(O92="yes",1,0)*'Grading Scale'!E$12)+(IF(P92="yes",1,0)*'Grading Scale'!E$13))/'Grading Scale'!E$14*100,0), "") -> 0 | T92: =IF(ISNUMBER(S92),VLOOKUP(S92,'Grading Scale'!$A$2:$B$14, 2), "") -> F
A93: 42396 | B93: Hawaii | C93: Checkbook | D93: =IF(NOT(ISBLANK(C93)), VLOOKUP(C93,'Dataset Descriptions'!$A$2:$B$10, 2, FALSE), "") -> Transaction-level, per-agency spending records. | E93: yes | F93: yes | G93: yes | H93: yes | I93: yes | J93: yes | K93: yes | L93: no | M93: no | N93: yes | O93: yes | P93: no | Q93: https://data.hawaii.gov/dataset/Expenditures/snda-zbsg | R93: Incomplete, because it lacks a description of the purpose of the expense (beyond a general category). Verifiable because the data is delivered via HTTPS. As of the date of this survey, the data had not been updated in 7 months. | S93: =IF(NOT(ISBLANK(E93)), ROUND(((IF(E93="yes",1,0)*'Grading Scale'!E$2)+(IF(F93="yes",1,0)*'Grading Scale'!E$3)+(IF(G93="yes",1,0)*'Grading Scale'!E$4)+(IF(H93="yes",1,0)*'Grading Scale'!E$5)+(IF(I93="yes",1,0)*'Grading Scale'!E$6)+(IF(J93="yes",1,0)*'Grading Scale'!E$7)+(IF(K93="yes",1,0)*'Grading Scale'!E$8)+(IF(L93="yes",1,0)*'Grading Scale'!E$9)+(IF(M93="yes",1,0)*'Grading Scale'!E$10)+(IF(N93="yes",1,0)*'Grading Scale'!E$11)+(IF(O93="yes",1,0)*'Grading Scale'!E$12)+(IF(P93="yes",1,0)*'Grading Scale'!E$13))/'Grading Scale'!E$14*100,0), "") -> 85 | T93: =IF(ISNUMBER(S93),VLOOKUP(S93,'Grading Scale'!$A$2:$B$14, 2), "") -> B
A94: 42396 | B94: Hawaii | C94: Companies | D94: =IF(NOT(ISBLANK(C94)), VLOOKUP(C94,'Dataset Descriptions'!$A$2:$B$10, 2, FALSE), "") -> The register of all corporations that exist in the state. | E94: yes | F94: yes | G94: yes | H94: no | I94: yes | J94: yes | K94: unsure | L94: no | M94: yes | N94: no | O94: unsure | P94: unsure | Q94: https://hbe.ehawaii.gov/listbuilder/ | R94: Data costs 5¢/record, or $1,000/month for access to the entire database. After paying, it takes up to 24 hours to receive an email with a link to download the data. In our test, it took 19 hours. Data is provided as a collection of CSV files, each of which represents a different data table. They also allow browsing the data on-screen at no charge. The site says that information is copyright "Hawaii Information Consortium, LLC"—it appears that this is a private company that has an exclusive contract to sell state data and run state websites. This dataset will be graded fully when the email with the link arrives. | S94: =IF(NOT(ISBLANK(E94)), ROUND(((IF(E94="yes",1,0)*'Grading Scale'!E$2)+(IF(F94="yes",1,0)*'Grading Scale'!E$3)+(IF(G94="yes",1,0)*'Grading Scale'!E$4)+(IF(H94="yes",1,0)*'Grading Scale'!E$5)+(IF(I94="yes",1,0)*'Grading Scale'!E$6)+(IF(J94="yes",1,0)*'Grading Scale'!E$7)+(IF(K94="yes",1,0)*'Grading Scale'!E$8)+(IF(L94="yes",1,0)*'Grading Scale'!E$9)+(IF(M94="yes",1,0)*'Grading Scale'!E$10)+(IF(N94="yes",1,0)*'Grading Scale'!E$11)+(IF(O94="yes",1,0)*'Grading Scale'!E$12)+(IF(P94="yes",1,0)*'Grading Scale'!E$13))/'Grading Scale'!E$14*100,0), "") -> 60 | T94: =IF(ISNUMBER(S94),VLOOKUP(S94,'Grading Scale'!$A$2:$B$14, 2), "") -> D−
A95: 42397 | B95: Hawaii | C95: Incarceration | D95: =IF(NOT(ISBLANK(C95)), VLOOKUP(C95,'Dataset Descriptions'!$A$2:$B$10, 2, FALSE), "") -> Per-facility inmate population records. | E95: yes | F95: yes | G95: yes | H95: yes | I95: yes | J95: no | K95: no | L95: no | M95: no | N95: no | O95: no | P95: no | Q95: http://dps.hawaii.gov/about/divisions/corrections/ | R95: This is a computer-generated document that has been printed out, scanned in as an image, and turned into a PDF. Ostensibly updated monthly, the current report is from over a year ago. | S95: =IF(NOT(ISBLANK(E95)), ROUND(((IF(E95="yes",1,0)*'Grading Scale'!E$2)+(IF(F95="yes",1,0)*'Grading Scale'!E$3)+(IF(G95="yes",1,0)*'Grading Scale'!E$4)+(IF(H95="yes",1,0)*'Grading Scale'!E$5)+(IF(I95="yes",1,0)*'Grading Scale'!E$6)+(IF(J95="yes",1,0)*'Grading Scale'!E$7)+(IF(K95="yes",1,0)*'Grading Scale'!E$8)+(IF(L95="yes",1,0)*'Grading Scale'!E$9)+(IF(M95="yes",1,0)*'Grading Scale'!E$10)+(IF(N95="yes",1,0)*'Grading Scale'!E$11)+(IF(O95="yes",1,0)*'Grading Scale'!E$12)+(IF(P95="yes",1,0)*'Grading Scale'!E$13))/'Grading Scale'!E$14*100,0), "") -> 30 | T95: =IF(ISNUMBER(S95),VLOOKUP(S95,'Grading Scale'!$A$2:$B$14, 2), "") -> F
A96: 42396 | B96: Hawaii | C96: Legislation | D96: =IF(NOT(ISBLANK(C96)), VLOOKUP(C96,'Dataset Descriptions'!$A$2:$B$10, 2, FALSE), "") -> Bills before the legislature, and the legislators that comprise it. | E96: yes | F96: yes | G96: yes | H96: yes | I96: yes | J96: no | K96: yes | L96: yes | M96: yes | N96: no | O96: no | P96: yes | Q96: http://www.capitol.hawaii.gov/ | R96: There is bulk data of state legislators (https://data.hawaii.gov/Government-Wide-Support/State-of-Hawaii-Elected-Officials/m6cf-4bb7), but it hasn't been updated in over 3 years, and is no longer accurate. This legislature does something unusual in providing access to raw directory listings of bills, resolutions, hearing notices, attendence, etc., as PDF and HTML files. This is not the same as providing access to data, certainly, but it is laudible that they provide bulk access to the information that they have, as they have it, and for that reason we have scored them as providing bulk access, even though that access isn't to actual data. | S96: =IF(NOT(ISBLANK(E96)), ROUND(((IF(E96="yes",1,0)*'Grading Scale'!E$2)+(IF(F96="yes",1,0)*'Grading Scale'!E$3)+(IF(G96="yes",1,0)*'Grading Scale'!E$4)+(IF(H96="yes",1,0)*'Grading Scale'!E$5)+(IF(I96="yes",1,0)*'Grading Scale'!E$6)+(IF(J96="yes",1,0)*'Grading Scale'!E$7)+(IF(K96="yes",1,0)*'Grading Scale'!E$8)+(IF(L96="yes",1,0)*'Grading Scale'!E$9)+(IF(M96="yes",1,0)*'Grading Scale'!E$10)+(IF(N96="yes",1,0)*'Grading Scale'!E$11)+(IF(O96="yes",1,0)*'Grading Scale'!E$12)+(IF(P96="yes",1,0)*'Grading Scale'!E$13))/'Grading Scale'!E$14*100,0), "") -> 50 | T96: =IF(ISNUMBER(S96),VLOOKUP(S96,'Grading Scale'!$A$2:$B$14, 2), "") -> F
A97: 42397 | B97: Hawaii | C97: Population Projections | D97: =IF(NOT(ISBLANK(C97)), VLOOKUP(C97,'Dataset Descriptions'!$A$2:$B$10, 2, FALSE), "") -> Forecasts of municipal-level changes in population over coming years. | E97: yes | F97: yes | G97: yes | H97: yes | I97: yes | J97: yes | K97: yes | L97: no | M97: yes | N97: yes | O97: no | P97: no | Q97: http://dbedt.hawaii.gov/economic/databook/2012-individual/_01/ | R97: Incomplete, as it lacks GNIS IDs or FIPS codes for counties. Provided as an Excel file. | S97: =IF(NOT(ISBLANK(E97)), ROUND(((IF(E97="yes",1,0)*'Grading Scale'!E$2)+(IF(F97="yes",1,0)*'Grading Scale'!E$3)+(IF(G97="yes",1,0)*'Grading Scale'!E$4)+(IF(H97="yes",1,0)*'Grading Scale'!E$5)+(IF(I97="yes",1,0)*'Grading Scale'!E$6)+(IF(J97="yes",1,0)*'Grading Scale'!E$7)+(IF(K97="yes",1,0)*'Grading Scale'!E$8)+(IF(L97="yes",1,0)*'Grading Scale'!E$9)+(IF(M97="yes",1,0)*'Grading Scale'!E$10)+(IF(N97="yes",1,0)*'Grading Scale'!E$11)+(IF(O97="yes",1,0)*'Grading Scale'!E$12)+(IF(P97="yes",1,0)*'Grading Scale'!E$13))/'Grading Scale'!E$14*100,0), "") -> 85 | T97: =IF(ISNUMBER(S97),VLOOKUP(S97,'Grading Scale'!$A$2:$B$14, 2), "") -> B
A98: 42395 | B98: Hawaii | C98: Real Estate | D98: =IF(NOT(ISBLANK(C98)), VLOOKUP(C98,'Dataset Descriptions'!$A$2:$B$10, 2, FALSE), "") -> State-owned land and buildings. | E98: unsure | R98: By law (http://www.capitol.hawaii.gov/Archives/measure_indiv_Archives.aspx?billtype=SB&billnumber=722&year=2013), the Department of Accounting and General Services is to maintain this inventory, but as of a 2013 report (http://ags.hawaii.gov/wp-content/uploads/2012/09/act-110-comprehensive-asset-mgmt-system-2013.pdf), this had not been done. There has been no report in the intervening two years, and no data can be found on their website. | S98: =IF(NOT(ISBLANK(E98)), ROUND(((IF(E98="yes",1,0)*'Grading Scale'!E$2)+(IF(F98="yes",1,0)*'Grading Scale'!E$3)+(IF(G98="yes",1,0)*'Grading Scale'!E$4)+(IF(H98="yes",1,0)*'Grading Scale'!E$5)+(IF(I98="yes",1,0)*'Grading Scale'!E$6)+(IF(J98="yes",1,0)*'Grading Scale'!E$7)+(IF(K98="yes",1,0)*'Grading Scale'!E$8)+(IF(L98="yes",1,0)*'Grading Scale'!E$9)+(IF(M98="yes",1,0)*'Grading Scale'!E$10)+(IF(N98="yes",1,0)*'Grading Scale'!E$11)+(IF(O98="yes",1,0)*'Grading Scale'!E$12)+(IF(P98="yes",1,0)*'Grading Scale'!E$13))/'Grading Scale'!E$14*100,0), "") -> 0 | T98: =IF(ISNUMBER(S98),VLOOKUP(S98,'Grading Scale'!$A$2:$B$14, 2), "") -> F
A99: 42396 | B99: Hawaii | C99: Restaurant Inspections | D99: =IF(NOT(ISBLANK(C99)), VLOOKUP(C99,'Dataset Descriptions'!$A$2:$B$10, 2, FALSE), "") -> Health inspections of establishments that serve food to the public. | E99: unsure | F99: unsure | G99: unsure | H99: unsure | I99: no | J99: unsure | K99: unsure | L99: unsure | M99: unsure | N99: no | O99: unsure | P99: unsure | R99: Apparently Hawaii used to have such a system, but they had a lot of trouble with their vendor, and replaced them in mid-2015. That no system can now be found seems like evidence that they have yet to replace it. | S99: =IF(NOT(ISBLANK(E99)), ROUND(((IF(E99="yes",1,0)*'Grading Scale'!E$2)+(IF(F99="yes",1,0)*'Grading Scale'!E$3)+(IF(G99="yes",1,0)*'Grading Scale'!E$4)+(IF(H99="yes",1,0)*'Grading Scale'!E$5)+(IF(I99="yes",1,0)*'Grading Scale'!E$6)+(IF(J99="yes",1,0)*'Grading Scale'!E$7)+(IF(K99="yes",1,0)*'Grading Scale'!E$8)+(IF(L99="yes",1,0)*'Grading Scale'!E$9)+(IF(M99="yes",1,0)*'Grading Scale'!E$10)+(IF(N99="yes",1,0)*'Grading Scale'!E$11)+(IF(O99="yes",1,0)*'Grading Scale'!E$12)+(IF(P99="yes",1,0)*'Grading Scale'!E$13))/'Grading Scale'!E$14*100,0), "") -> 0 | T99: =IF(ISNUMBER(S99),VLOOKUP(S99,'Grading Scale'!$A$2:$B$14, 2), "") -> F
A100: 42397 | B100: Hawaii | C100: Vehicle Crashes | D100: =IF(NOT(ISBLANK(C100)), VLOOKUP(C100,'Dataset Descriptions'!$A$2:$B$10, 2, FALSE), "") -> Incident-level reportable motor vehicle crash records. | E100: yes | F100: unsure | G100: unsure | H100: unsure | I100: unsure | J100: unsure | K100: unsure | L100: unsure | M100: unsure | N100: no | O100: unsure | P100: unsure | R100: There are multiple references to the fact that Hawaii collects crash data (for any accident with damages in excess of $3,000) and enters it into a centralized system, but no evidence of that system or its data can be found. | S100: =IF(NOT(ISBLANK(E100)), ROUND(((IF(E100="yes",1,0)*'Grading Scale'!E$2)+(IF(F100="yes",1,0)*'Grading Scale'!E$3)+(IF(G100="yes",1,0)*'Grading Scale'!E$4)+(IF(H100="yes",1,0)*'Grading Scale'!E$5)+(IF(I100="yes",1,0)*'Grading Scale'!E$6)+(IF(J100="yes",1,0)*'Grading Scale'!E$7)+(IF(K100="yes",1,0)*'Grading Scale'!E$8)+(IF(L100="yes",1,0)*'Grading Scale'!E$9)+(IF(M100="yes",1,0)*'Grading Scale'!E$10)+(IF(N100="yes",1,0)*'Grading Scale'!E$11)+(IF(O100="yes",1,0)*'Grading Scale'!E$12)+(IF(P100="yes",1,0)*'Grading Scale'!E$13))/'Grading Scale'!E$14*100,0), "") -> 0 | T100: =IF(ISNUMBER(S100),VLOOKUP(S100,'Grading Scale'!$A$2:$B$14, 2), "") -> F
...

Sheet Grading Scale
A1: Low Score | B1: Grade | D1: Criterion | E1: Points
A2: 0 | B2: F | D2: Exists | E2: 0
A3: =E14*0.6 -> 60 | B3: D− | D3: Digitized | E3: 5
A4: =E14*0.63 -> 63 | B4: D | D4: Public | E4: 5
A5: =E14*0.67 -> 67 | B5: D+ | D5: Free | E5: 15
A6: =E14*0.7 -> 70 | B6: C− | D6: Online | E6: 5
A7: =E14*0.73 -> 73 | B7: C | D7: Machine readable | E7: 40
A8: =E14*0.77 -> 77 | B8: C+ | D8: Available in bulk | E8: 5
A9: =E14*0.8 -> 80 | B9: B− | D9: No restrictions | E9: 5
A10: =E14*0.83 -> 83 | B10: B | D10: Up-to-date | E10: 5
A11: =E14*0.87 -> 87 | B11: B+ | D11: In the state repository | E11: 5
A12: =E14*0.9 -> 90 | B12: A− | D12: Verifiable | E12: 5
A13: =E14*0.93 -> 93 | B13: A | D13: Complete | E13: 5
A14: =E14*0.97 -> 97 | B14: A+ | E14: =SUM(E2:E13) -> 100

Sheet Dataset Descriptions
A1: Type | B1: Description
A2: Companies | B2: The register of all corporations that exist in the state.
A3: Incarceration | B3: Per-facility inmate population records.
A4: Real Estate | B4: State-owned land and buildings.
A5: Checkbook | B5: Transaction-level, per-agency spending records.
A6: Address Points | B6: The geographic coordinates for physical addresses.
A7: Legislation | B7: Bills before the legislature, and the legislators that comprise it.
A8: Restaurant Inspections | B8: Health inspections of establishments that serve food to the public.
A9: Population Projections | B9: Forecasts of municipal-level changes in population over coming years.
A10: Vehicle Crashes | B10: Incident-level reportable motor vehicle crash records.

Sheet Places
A1: Name | B1: Score | C1: Grade | D1: Repository URL | E1: Comments
A2: {=INDEX('Census Data'!$B$2:$B$504, MATCH(0, COUNTIF($A$1:A1, 'Census Data'!$B$2:$B$504), 0))} -> Alabama | B2: =ROUND(AVERAGEIF('Census Data'!B$1:B$1004,A2,'Census Data'!S$1:S$1004),0) -> 37 | C2: =VLOOKUP(B2,'Grading Scale'!$A$2:$B$14, 2) -> F
A3: {=INDEX('Census Data'!$B$2:$B$504, MATCH(0, COUNTIF($A$1:A2, 'Census Data'!$B$2:$B$504), 0))} -> Alaska | B3: =ROUND(AVERAGEIF('Census Data'!B$1:B$1004,A3,'Census Data'!S$1:S$1004),0) -> 47 | C3: =VLOOKUP(B3,'Grading Scale'!$A$2:$B$14, 2) -> F
A4: {=INDEX('Census Data'!$B$2:$B$504, MATCH(0, COUNTIF($A$1:A3, 'Census Data'!$B$2:$B$504), 0))} -> Arizona | B4: =ROUND(AVERAGEIF('Census Data'!B$1:B$1004,A4,'Census Data'!S$1:S$1004),0) -> 40 | C4: =VLOOKUP(B4,'Grading Scale'!$A$2:$B$14, 2) -> F
A5: {=INDEX('Census Data'!$B$2:$B$504, MATCH(0, COUNTIF($A$1:A4, 'Census Data'!$B$2:$B$504), 0))} -> Arkansas | B5: =ROUND(AVERAGEIF('Census Data'!B$1:B$1004,A5,'Census Data'!S$1:S$1004),0) -> 46 | C5: =VLOOKUP(B5,'Grading Scale'!$A$2:$B$14, 2) -> F
A6: {=INDEX('Census Data'!$B$2:$B$504, MATCH(0, COUNTIF($A$1:A5, 'Census Data'!$B$2:$B$504), 0))} -> California | B6: =ROUND(AVERAGEIF('Census Data'!B$1:B$1004,A6,'Census Data'!S$1:S$1004),0) -> 42 | C6: =VLOOKUP(B6,'Grading Scale'!$A$2:$B$14, 2) -> F | D6: http://data.ca.gov/
A7: {=INDEX('Census Data'!$B$2:$B$504, MATCH(0, COUNTIF($A$1:A6, 'Census Data'!$B$2:$B$504), 0))} -> Colorado | B7: =ROUND(AVERAGEIF('Census Data'!B$1:B$1004,A7,'Census Data'!S$1:S$1004),0) -> 57 | C7: =VLOOKUP(B7,'Grading Scale'!$A$2:$B$14, 2) -> F | D7: https://data.colorado.gov/
A8: {=INDEX('Census Data'!$B$2:$B$504, MATCH(0, COUNTIF($A$1:A7, 'Census Data'!$B$2:$B$504), 0))} -> Connecticut | B8: =ROUND(AVERAGEIF('Census Data'!B$1:B$1004,A8,'Census Data'!S$1:S$1004),0) -> 84 | C8: =VLOOKUP(B8,'Grading Scale'!$A$2:$B$14, 2) -> B | D8: https://data.ct.gov/
A9: {=INDEX('Census Data'!$B$2:$B$504, MATCH(0, COUNTIF($A$1:A8, 'Census Data'!$B$2:$B$504), 0))} -> Delaware | B9: =ROUND(AVERAGEIF('Census Data'!B$1:B$1004,A9,'Census Data'!S$1:S$1004),0) -> 48 | C9: =VLOOKUP(B9,'Grading Scale'!$A$2:$B$14, 2) -> F | D9: https://delaware.gov/topics/data
A10: {=INDEX('Census Data'!$B$2:$B$504, MATCH(0, COUNTIF($A$1:A9, 'Census Data'!$B$2:$B$504), 0))} -> Florida | B10: =ROUND(AVERAGEIF('Census Data'!B$1:B$1004,A10,'Census Data'!S$1:S$1004),0) -> 43 | C10: =VLOOKUP(B10,'Grading Scale'!$A$2:$B$14, 2) -> F
A11: {=INDEX('Census Data'!$B$2:$B$504, MATCH(0, COUNTIF($A$1:A10, 'Census Data'!$B$2:$B$504), 0))} -> Georgia | B11: =ROUND(AVERAGEIF('Census Data'!B$1:B$1004,A11,'Census Data'!S$1:S$1004),0) -> 39 | C11: =VLOOKUP(B11,'Grading Scale'!$A$2:$B$14, 2) -> F | D11: http://www.open.georgia.gov/
A12: {=INDEX('Census Data'!$B$2:$B$504, MATCH(0, COUNTIF($A$1:A11, 'Census Data'!$B$2:$B$504), 0))} -> Hawaii | B12: =ROUND(AVERAGEIF('Census Data'!B$1:B$1004,A12,'Census Data'!S$1:S$1004),0) -> 34 | C12: =VLOOKUP(B12,'Grading Scale'!$A$2:$B$14, 2) -> F | D12: https://data.hawaii.gov/
A13: {=INDEX('Census Data'!$B$2:$B$504, MATCH(0, COUNTIF($A$1:A12, 'Census Data'!$B$2:$B$504), 0))} -> Idaho | B13: =ROUND(AVERAGEIF('Census Data'!B$1:B$1004,A13,'Census Data'!S$1:S$1004),0) -> 21 | C13: =VLOOKUP(B13,'Grading Scale'!$A$2:$B$14, 2) -> F
A14: {=INDEX('Census Data'!$B$2:$B$504, MATCH(0, COUNTIF($A$1:A13, 'Census Data'!$B$2:$B$504), 0))} -> Illinois | B14: =ROUND(AVERAGEIF('Census Data'!B$1:B$1004,A14,'Census Data'!S$1:S$1004),0) -> 29 | C14: =VLOOKUP(B14,'Grading Scale'!$A$2:$B$14, 2) -> F | D14: https://data.illinois.gov/
A15: {=INDEX('Census Data'!$B$2:$B$504, MATCH(0, COUNTIF($A$1:A14, 'Census Data'!$B$2:$B$504), 0))} -> Indiana | B15: =ROUND(AVERAGEIF('Census Data'!B$1:B$1004,A15,'Census Data'!S$1:S$1004),0) -> 56 | C15: =VLOOKUP(B15,'Grading Scale'!$A$2:$B$14, 2) -> F
A16: {=INDEX('Census Data'!$B$2:$B$504, MATCH(0, COUNTIF($A$1:A15, 'Census Data'!$B$2:$B$504), 0))} -> Iowa | B16: =ROUND(AVERAGEIF('Census Data'!B$1:B$1004,A16,'Census Data'!S$1:S$1004),0) -> 61 | C16: =VLOOKUP(B16,'Grading Scale'!$A$2:$B$14, 2) -> D− | D16: https://data.iowa.gov/
A17: {=INDEX('Census Data'!$B$2:$B$504, MATCH(0, COUNTIF($A$1:A16, 'Census Data'!$B$2:$B$504), 0))} -> Kansas | B17: =ROUND(AVERAGEIF('Census Data'!B$1:B$1004,A17,'Census Data'!S$1:S$1004),0) -> 37 | C17: =VLOOKUP(B17,'Grading Scale'!$A$2:$B$14, 2) -> F
A18: {=INDEX('Census Data'!$B$2:$B$504, MATCH(0, COUNTIF($A$1:A17, 'Census Data'!$B$2:$B$504), 0))} -> Kentucky | B18: =ROUND(AVERAGEIF('Census Data'!B$1:B$1004,A18,'Census Data'!S$1:S$1004),0) -> 47 | C18: =VLOOKUP(B18,'Grading Scale'!$A$2:$B$14, 2) -> F
A19: {=INDEX('Census Data'!$B$2:$B$504, MATCH(0, COUNTIF($A$1:A18, 'Census Data'!$B$2:$B$504), 0))} -> Louisiana | B19: =ROUND(AVERAGEIF('Census Data'!B$1:B$1004,A19,'Census Data'!S$1:S$1004),0) -> 51 | C19: =VLOOKUP(B19,'Grading Scale'!$A$2:$B$14, 2) -> F
A20: {=INDEX('Census Data'!$B$2:$B$504, MATCH(0, COUNTIF($A$1:A19, 'Census Data'!$B$2:$B$504), 0))} -> Maine | B20: =ROUND(AVERAGEIF('Census Data'!B$1:B$1004,A20,'Census Data'!S$1:S$1004),0) -> 47 | C20: =VLOOKUP(B20,'Grading Scale'!$A$2:$B$14, 2) -> F | D20: https://data.maine.gov/
A21: {=INDEX('Census Data'!$B$2:$B$504, MATCH(0, COUNTIF($A$1:A20, 'Census Data'!$B$2:$B$504), 0))} -> Maryland | B21: =ROUND(AVERAGEIF('Census Data'!B$1:B$1004,A21,'Census Data'!S$1:S$1004),0) -> 58 | C21: =VLOOKUP(B21,'Grading Scale'!$A$2:$B$14, 2) -> F | D21: https://data.md.gov/
A22: {=INDEX('Census Data'!$B$2:$B$504, MATCH(0, COUNTIF($A$1:A21, 'Census Data'!$B$2:$B$504), 0))} -> Massachusetts | B22: =ROUND(AVERAGEIF('Census Data'!B$1:B$1004,A22,'Census Data'!S$1:S$1004),0) -> 53 | C22: =VLOOKUP(B22,'Grading Scale'!$A$2:$B$14, 2) -> F | D22: http://www.mass.gov/opendata/
A23: {=INDEX('Census Data'!$B$2:$B$504, MATCH(0, COUNTIF($A$1:A22, 'Census Data'!$B$2:$B$504), 0))} -> Michigan | B23: =ROUND(AVERAGEIF('Census Data'!B$1:B$1004,A23,'Census Data'!S$1:S$1004),0) -> 36 | C23: =VLOOKUP(B23,'Grading Scale'!$A$2:$B$14, 2) -> F | D23: https://data.michigan.gov/
A24: {=INDEX('Census Data'!$B$2:$B$504, MATCH(0, COUNTIF($A$1:A23, 'Census Data'!$B$2:$B$504), 0))} -> Minnesota | B24: =ROUND(AVERAGEIF('Census Data'!B$1:B$1004,A24,'Census Data'!S$1:S$1004),0) -> 42 | C24: =VLOOKUP(B24,'Grading Scale'!$A$2:$B$14, 2) -> F | D24: http://www.state.mn.us/opendata/
A25: {=INDEX('Census Data'!$B$2:$B$504, MATCH(0, COUNTIF($A$1:A24, 'Census Data'!$B$2:$B$504), 0))} -> Mississippi | B25: =ROUND(AVERAGEIF('Census Data'!B$1:B$1004,A25,'Census Data'!S$1:S$1004),0) -> 37 | C25: =VLOOKUP(B25,'Grading Scale'!$A$2:$B$14, 2) -> F | D25: https://data.mo.gov/
A26: {=INDEX('Census Data'!$B$2:$B$504, MATCH(0, COUNTIF($A$1:A25, 'Census Data'!$B$2:$B$504), 0))} -> Missouri | B26: =ROUND(AVERAGEIF('Census Data'!B$1:B$1004,A26,'Census Data'!S$1:S$1004),0) -> 46 | C26: =VLOOKUP(B26,'Grading Scale'!$A$2:$B$14, 2) -> F | D26: http://data.mt.gov/
A27: {=INDEX('Census Data'!$B$2:$B$504, MATCH(0, COUNTIF($A$1:A26, 'Census Data'!$B$2:$B$504), 0))} -> Montana | B27: =ROUND(AVERAGEIF('Census Data'!B$1:B$1004,A27,'Census Data'!S$1:S$1004),0) -> 66 | C27: =VLOOKUP(B27,'Grading Scale'!$A$2:$B$14, 2) -> D
A28: {=INDEX('Census Data'!$B$2:$B$504, MATCH(0, COUNTIF($A$1:A27, 'Census Data'!$B$2:$B$504), 0))} -> Nebraska | B28: =ROUND(AVERAGEIF('Census Data'!B$1:B$1004,A28,'Census Data'!S$1:S$1004),0) -> 46 | C28: =VLOOKUP(B28,'Grading Scale'!$A$2:$B$14, 2) -> F
A29: {=INDEX('Census Data'!$B$2:$B$504, MATCH(0, COUNTIF($A$1:A28, 'Census Data'!$B$2:$B$504), 0))} -> Nevada | B29: =ROUND(AVERAGEIF('Census Data'!B$1:B$1004,A29,'Census Data'!S$1:S$1004),0) -> 43 | C29: =VLOOKUP(B29,'Grading Scale'!$A$2:$B$14, 2) -> F | D29: http://data.nh.gov/ | E29: Kentucky claims copyright over nearly all of their datasets (with a copyright statement in the footer), despite that they almost certainly lack the legal authority to do so. Also, their open data site is really a late-'00s-style open finances site, not an open data repository in the modern sense.
A30: {=INDEX('Census Data'!$B$2:$B$504, MATCH(0, COUNTIF($A$1:A29, 'Census Data'!$B$2:$B$504), 0))} -> New Hampshire | B30: =ROUND(AVERAGEIF('Census Data'!B$1:B$1004,A30,'Census Data'!S$1:S$1004),0) -> 53 | C30: =VLOOKUP(B30,'Grading Scale'!$A$2:$B$14, 2) -> F | D30: https://data.nj.gov/
A31: {=INDEX('Census Data'!$B$2:$B$504, MATCH(0, COUNTIF($A$1:A30, 'Census Data'!$B$2:$B$504), 0))} -> New Jersey | B31: =ROUND(AVERAGEIF('Census Data'!B$1:B$1004,A31,'Census Data'!S$1:S$1004),0) -> 43 | C31: =VLOOKUP(B31,'Grading Scale'!$A$2:$B$14, 2) -> F
A32: {=INDEX('Census Data'!$B$2:$B$504, MATCH(0, COUNTIF($A$1:A31, 'Census Data'!$B$2:$B$504), 0))} -> New Mexico | B32: =ROUND(AVERAGEIF('Census Data'!B$1:B$1004,A32,'Census Data'!S$1:S$1004),0) -> 40 | C32: =VLOOKUP(B32,'Grading Scale'!$A$2:$B$14, 2) -> F | D32: https://data.ny.gov/ | E32: Census is inaccurate pending modification of the census software to allow scoring of the legislature. (It keeps its data on two separate sites, one for each chamber.)
A33: {=INDEX('Census Data'!$B$2:$B$504, MATCH(0, COUNTIF($A$1:A32, 'Census Data'!$B$2:$B$504), 0))} -> New York | B33: =ROUND(AVERAGEIF('Census Data'!B$1:B$1004,A33,'Census Data'!S$1:S$1004),0) -> 74 | C33: =VLOOKUP(B33,'Grading Scale'!$A$2:$B$14, 2) -> C
A34: {=INDEX('Census Data'!$B$2:$B$504, MATCH(0, COUNTIF($A$1:A33, 'Census Data'!$B$2:$B$504), 0))} -> North Carolina | B34: =ROUND(AVERAGEIF('Census Data'!B$1:B$1004,A34,'Census Data'!S$1:S$1004),0) -> 56 | C34: =VLOOKUP(B34,'Grading Scale'!$A$2:$B$14, 2) -> F
A35: {=INDEX('Census Data'!$B$2:$B$504, MATCH(0, COUNTIF($A$1:A34, 'Census Data'!$B$2:$B$504), 0))} -> North Dakota | B35: =ROUND(AVERAGEIF('Census Data'!B$1:B$1004,A35,'Census Data'!S$1:S$1004),0) -> 28 | C35: =VLOOKUP(B35,'Grading Scale'!$A$2:$B$14, 2) -> F
A36: {=INDEX('Census Data'!$B$2:$B$504, MATCH(0, COUNTIF($A$1:A35, 'Census Data'!$B$2:$B$504), 0))} -> Ohio | B36: =ROUND(AVERAGEIF('Census Data'!B$1:B$1004,A36,'Census Data'!S$1:S$1004),0) -> 67 | C36: =VLOOKUP(B36,'Grading Scale'!$A$2:$B$14, 2) -> D+ | D36: https://data.ok.gov/
A37: {=INDEX('Census Data'!$B$2:$B$504, MATCH(0, COUNTIF($A$1:A36, 'Census Data'!$B$2:$B$504), 0))} -> Oklahoma | B37: =ROUND(AVERAGEIF('Census Data'!B$1:B$1004,A37,'Census Data'!S$1:S$1004),0) -> 58 | C37: =VLOOKUP(B37,'Grading Scale'!$A$2:$B$14, 2) -> F | D37: https://data.oregon.gov/
A38: {=INDEX('Census Data'!$B$2:$B$504, MATCH(0, COUNTIF($A$1:A37, 'Census Data'!$B$2:$B$504), 0))} -> Oregon | B38: =ROUND(AVERAGEIF('Census Data'!B$1:B$1004,A38,'Census Data'!S$1:S$1004),0) -> 51 | C38: =VLOOKUP(B38,'Grading Scale'!$A$2:$B$14, 2) -> F
A39: {=INDEX('Census Data'!$B$2:$B$504, MATCH(0, COUNTIF($A$1:A38, 'Census Data'!$B$2:$B$504), 0))} -> Pennsylvania | B39: =ROUND(AVERAGEIF('Census Data'!B$1:B$1004,A39,'Census Data'!S$1:S$1004),0) -> 39 | C39: =VLOOKUP(B39,'Grading Scale'!$A$2:$B$14, 2) -> F | D39: https://data.pr.gov/
A40: {=INDEX('Census Data'!$B$2:$B$504, MATCH(0, COUNTIF($A$1:A39, 'Census Data'!$B$2:$B$504), 0))} -> Puerto Rico | B40: =ROUND(AVERAGEIF('Census Data'!B$1:B$1004,A40,'Census Data'!S$1:S$1004),0) -> 43 | C40: =VLOOKUP(B40,'Grading Scale'!$A$2:$B$14, 2) -> F | D40: http://www.ri.gov/data/
A41: {=INDEX('Census Data'!$B$2:$B$504, MATCH(0, COUNTIF($A$1:A40, 'Census Data'!$B$2:$B$504), 0))} -> Rhode Island | B41: =ROUND(AVERAGEIF('Census Data'!B$1:B$1004,A41,'Census Data'!S$1:S$1004),0) -> 47 | C41: =VLOOKUP(B41,'Grading Scale'!$A$2:$B$14, 2) -> F
A42: {=INDEX('Census Data'!$B$2:$B$504, MATCH(0, COUNTIF($A$1:A41, 'Census Data'!$B$2:$B$504), 0))} -> South Carolina | B42: =ROUND(AVERAGEIF('Census Data'!B$1:B$1004,A42,'Census Data'!S$1:S$1004),0) -> 58 | C42: =VLOOKUP(B42,'Grading Scale'!$A$2:$B$14, 2) -> F
A43: {=INDEX('Census Data'!$B$2:$B$504, MATCH(0, COUNTIF($A$1:A42, 'Census Data'!$B$2:$B$504), 0))} -> South Dakota | B43: =ROUND(AVERAGEIF('Census Data'!B$1:B$1004,A43,'Census Data'!S$1:S$1004),0) -> 46 | C43: =VLOOKUP(B43,'Grading Scale'!$A$2:$B$14, 2) -> F | D43: https://www.tn.gov/transparenttn
A44: {=INDEX('Census Data'!$B$2:$B$504, MATCH(0, COUNTIF($A$1:A43, 'Census Data'!$B$2:$B$504), 0))} -> Tennessee | B44: =ROUND(AVERAGEIF('Census Data'!B$1:B$1004,A44,'Census Data'!S$1:S$1004),0) -> 51 | C44: =VLOOKUP(B44,'Grading Scale'!$A$2:$B$14, 2) -> F | D44: https://data.texas.gov/
A45: {=INDEX('Census Data'!$B$2:$B$504, MATCH(0, COUNTIF($A$1:A44, 'Census Data'!$B$2:$B$504), 0))} -> Texas | B45: =ROUND(AVERAGEIF('Census Data'!B$1:B$1004,A45,'Census Data'!S$1:S$1004),0) -> 56 | C45: =VLOOKUP(B45,'Grading Scale'!$A$2:$B$14, 2) -> F | D45: http://opendata.utah.gov/
A46: {=INDEX('Census Data'!$B$2:$B$504, MATCH(0, COUNTIF($A$1:A45, 'Census Data'!$B$2:$B$504), 0))} -> Utah | B46: =ROUND(AVERAGEIF('Census Data'!B$1:B$1004,A46,'Census Data'!S$1:S$1004),0) -> 42 | C46: =VLOOKUP(B46,'Grading Scale'!$A$2:$B$14, 2) -> F
A47: {=INDEX('Census Data'!$B$2:$B$504, MATCH(0, COUNTIF($A$1:A46, 'Census Data'!$B$2:$B$504), 0))} -> Vermont | B47: =ROUND(AVERAGEIF('Census Data'!B$1:B$1004,A47,'Census Data'!S$1:S$1004),0) -> 50 | C47: =VLOOKUP(B47,'Grading Scale'!$A$2:$B$14, 2) -> F | D47: https://data.vermont.gov/
A48: {=INDEX('Census Data'!$B$2:$B$504, MATCH(0, COUNTIF($A$1:A47, 'Census Data'!$B$2:$B$504), 0))} -> Virginia | B48: =ROUND(AVERAGEIF('Census Data'!B$1:B$1004,A48,'Census Data'!S$1:S$1004),0) -> 74 | C48: =VLOOKUP(B48,'Grading Scale'!$A$2:$B$14, 2) -> C | D48: https://data.wa.gov/
A49: {=INDEX('Census Data'!$B$2:$B$504, MATCH(0, COUNTIF($A$1:A48, 'Census Data'!$B$2:$B$504), 0))} -> Washington | B49: =ROUND(AVERAGEIF('Census Data'!B$1:B$1004,A49,'Census Data'!S$1:S$1004),0) -> 79 | C49: =VLOOKUP(B49,'Grading Scale'!$A$2:$B$14, 2) -> C+ | D49: http://opendata.dc.gov/
A50: {=INDEX('Census Data'!$B$2:$B$504, MATCH(0, COUNTIF($A$1:A49, 'Census Data'!$B$2:$B$504), 0))} -> Washington DC | B50: =ROUND(AVERAGEIF('Census Data'!B$1:B$1004,A50,'Census Data'!S$1:S$1004),0) -> 78 | C50: =VLOOKUP(B50,'Grading Scale'!$A$2:$B$14, 2) -> C+
A51: {=INDEX('Census Data'!$B$2:$B$504, MATCH(0, COUNTIF($A$1:A50, 'Census Data'!$B$2:$B$504), 0))} -> West Virginia | B51: =ROUND(AVERAGEIF('Census Data'!B$1:B$1004,A51,'Census Data'!S$1:S$1004),0) -> 34 | C51: =VLOOKUP(B51,'Grading Scale'!$A$2:$B$14, 2) -> F
A52: {=INDEX('Census Data'!$B$2:$B$504, MATCH(0, COUNTIF($A$1:A51, 'Census Data'!$B$2:$B$504), 0))} -> Wisconsin | B52: =ROUND(AVERAGEIF('Census Data'!B$1:B$1004,A52,'Census Data'!S$1:S$1004),0) -> 49 | C52: =VLOOKUP(B52,'Grading Scale'!$A$2:$B$14, 2) -> F
A53: {=INDEX('Census Data'!$B$2:$B$504, MATCH(0, COUNTIF($A$1:A52, 'Census Data'!$B$2:$B$504), 0))} -> Wyoming | B53: =ROUND(AVERAGEIF('Census Data'!B$1:B$1004,A53,'Census Data'!S$1:S$1004),0) -> 31 | C53: =VLOOKUP(B53,'Grading Scale'!$A$2:$B$14, 2) -> F
